{
  "updated_at": "2026-06-14T13:27:03.296Z",
  "source": "coinmarketcap",
  "note": "Triage, pas un prédicteur. Le tracker dit si le score vaut quelque chose.",
  "weights_mode": "appris",
  "weights": {
    "float_quality": 0.6,
    "momentum_24h": 0.075,
    "momentum_7d": 0.1,
    "momentum_30d": 0.075,
    "volume_surge": 0.15
  },
  "dd_status": {
    "coingecko": true,
    "cg": 0,
    "dd": 37
  },
  "count": 50,
  "candidates": [
    {
      "id": 3701,
      "symbol": "RIF",
      "name": "Rootstock Infrastructure Framework",
      "price": 0.09979546496959404,
      "market_cap": 99795464.96959405,
      "volume_24h": 29639456.80963621,
      "pct_7d": 51.75466202,
      "pct_30d": 29.4801838,
      "float_ratio": 1,
      "score": 0.8262639182935598,
      "parts": {
        "float_quality": 1,
        "momentum_24h": 0.20070890733333335,
        "momentum_7d": 1,
        "momentum_30d": 0.294801838,
        "volume_surge": 0.5940040826237313
      },
      "dd": {
        "tvl": null,
        "category": "Solana Ecosystem",
        "fees24h": null,
        "liquidity_usd": null,
        "pair_age_days": null,
        "token_age_days": null,
        "flags": []
      }
    },
    {
      "id": 40029,
      "symbol": "MANIFEST",
      "name": "Manifesting (manifesting.meme)",
      "price": 0.04525298721750321,
      "market_cap": 40727676.36795232,
      "volume_24h": 2375211.67604822,
      "pct_7d": 48.28771851,
      "pct_30d": 129116.31152364,
      "float_ratio": 1,
      "score": 0.8175574073109649,
      "parts": {
        "float_quality": 1,
        "momentum_24h": 0.37981553100000004,
        "momentum_7d": 0.9657543702,
        "momentum_30d": 1,
        "volume_surge": 0.11663870310643208
      },
      "dd": {
        "tvl": null,
        "category": "Meme",
        "fees24h": null,
        "liquidity_usd": 1084739.96,
        "pair_age_days": 28,
        "token_age_days": null,
        "flags": []
      }
    },
    {
      "id": 35537,
      "symbol": "JELLYJELLY",
      "name": "Jelly-My-Jelly",
      "price": 0.07421954120701361,
      "market_cap": 74219474.33520699,
      "volume_24h": 9647056.3772236,
      "pct_7d": 30.91206199,
      "pct_30d": 30.79516714,
      "float_ratio": 1,
      "score": 0.7941746390304644,
      "parts": {
        "float_quality": 1,
        "momentum_24h": 0.936801372,
        "momentum_7d": 0.6182412398,
        "momentum_30d": 0.3079516714,
        "volume_surge": 0.25996024530309536
      },
      "dd": {
        "tvl": null,
        "category": "Solana Ecosystem",
        "fees24h": null,
        "liquidity_usd": 4572184,
        "pair_age_days": 500,
        "token_age_days": null,
        "flags": []
      }
    },
    {
      "id": 34118,
      "symbol": "BANANAS31",
      "name": "Banana For Scale",
      "price": 0.009717285202594107,
      "market_cap": 97172852.02594107,
      "volume_24h": 38592580.21575899,
      "pct_7d": -10.02268815,
      "pct_30d": -19.23166157,
      "float_ratio": 1,
      "score": 0.7853967439706432,
      "parts": {
        "float_quality": 1,
        "momentum_24h": 0.8833408603333334,
        "momentum_7d": 0,
        "momentum_30d": 0,
        "volume_surge": 0.7943078629709538
      },
      "dd": {
        "tvl": null,
        "category": "BNB Chain Ecosystem",
        "fees24h": null,
        "liquidity_usd": 4170684.6,
        "pair_age_days": 573,
        "token_age_days": null,
        "flags": []
      }
    },
    {
      "id": 28850,
      "symbol": "NOT",
      "name": "Notcoin",
      "price": 0.00047183800089360217,
      "market_cap": 46914548.50238015,
      "volume_24h": 25734800.70419297,
      "pct_7d": 24.16823245,
      "pct_30d": -10.79894004,
      "float_ratio": 0.9704902864596566,
      "score": 0.780630636775794,
      "parts": {
        "float_quality": 0.9704902864596566,
        "momentum_24h": 0,
        "momentum_7d": 0.48336464900000004,
        "momentum_30d": 0,
        "volume_surge": 1
      },
      "dd": {
        "tvl": null,
        "category": "Gaming (GameFi)",
        "fees24h": null,
        "liquidity_usd": 208417.14,
        "pair_age_days": 759,
        "token_age_days": null,
        "flags": []
      }
    },
    {
      "id": 35766,
      "symbol": "SIREN",
      "name": "siren",
      "price": 0.07439114110517232,
      "market_cap": 53939763.460935816,
      "volume_24h": 155676232.8493462,
      "pct_7d": -94.25591736,
      "pct_30d": -85.57730839,
      "float_ratio": 1,
      "score": 0.7500000000000001,
      "parts": {
        "float_quality": 1,
        "momentum_24h": 0,
        "momentum_7d": 0,
        "momentum_30d": 0,
        "volume_surge": 1
      },
      "dd": {
        "tvl": null,
        "category": "BNB Chain Ecosystem",
        "fees24h": null,
        "liquidity_usd": 2666018.52,
        "pair_age_days": 490,
        "token_age_days": null,
        "flags": []
      }
    },
    {
      "id": 29743,
      "symbol": "BRETT",
      "name": "Brett (Based)",
      "price": 0.006492949132143786,
      "market_cap": 64929475.37945013,
      "volume_24h": 17649398.7583879,
      "pct_7d": 21.33044214,
      "pct_30d": -26.3655952,
      "float_ratio": 1,
      "score": 0.743255051286537,
      "parts": {
        "float_quality": 1,
        "momentum_24h": 0.253959003,
        "momentum_7d": 0.4266088428,
        "momentum_30d": 0,
        "volume_surge": 0.5436482785435797
      },
      "dd": {
        "tvl": null,
        "category": "BNB Chain Ecosystem",
        "fees24h": null,
        "liquidity_usd": null,
        "pair_age_days": null,
        "token_age_days": null,
        "flags": []
      }
    },
    {
      "id": 28301,
      "symbol": "MEME",
      "name": "Memecoin",
      "price": 0.000623965299474733,
      "market_cap": 39632021.96492262,
      "volume_24h": 25466670.03902869,
      "pct_7d": 0.86123125,
      "pct_30d": 7.49299681,
      "float_ratio": 0.920527360111111,
      "score": 0.7374390754741666,
      "parts": {
        "float_quality": 0.920527360111111,
        "momentum_24h": 0.3704059906666667,
        "momentum_7d": 0.017224625,
        "momentum_30d": 0.07492996810000001,
        "volume_surge": 1
      },
      "dd": {
        "tvl": 46462.55306681739,
        "category": "Dexs",
        "fees24h": null,
        "liquidity_usd": null,
        "pair_age_days": null,
        "token_age_days": null,
        "flags": [
          {
            "k": "TVL sans revenu",
            "t": "warn"
          }
        ]
      }
    },
    {
      "id": 17799,
      "symbol": "AXL",
      "name": "Axelar",
      "price": 0.0458746830456792,
      "market_cap": 54424609.39048327,
      "volume_24h": 24324481.4349222,
      "pct_7d": 10.58792502,
      "pct_30d": -29.67304026,
      "float_ratio": 0.9536488855947199,
      "score": 0.7274468865703133,
      "parts": {
        "float_quality": 0.9536488855947199,
        "momentum_24h": 0,
        "momentum_7d": 0.2117585004,
        "momentum_30d": 0,
        "volume_surge": 0.8938780344898755
      },
      "dd": {
        "tvl": 143399672.2851175,
        "category": "Bridge",
        "fees24h": 25,
        "liquidity_usd": null,
        "pair_age_days": null,
        "token_age_days": null,
        "flags": [
          {
            "k": "TVL sans revenu",
            "t": "warn"
          }
        ]
      }
    },
    {
      "id": 33788,
      "symbol": "PNUT",
      "name": "Peanut the Squirrel",
      "price": 0.04371773905669013,
      "market_cap": 43710830.00709144,
      "volume_24h": 15297638.57292768,
      "pct_7d": 6.00356925,
      "pct_30d": -27.51999296,
      "float_ratio": 1,
      "score": 0.7169992324761099,
      "parts": {
        "float_quality": 1,
        "momentum_24h": 0,
        "momentum_7d": 0.120071385,
        "momentum_30d": 0,
        "volume_surge": 0.6999472931740652
      },
      "dd": {
        "tvl": null,
        "category": "Meme",
        "fees24h": null,
        "liquidity_usd": 2469515.79,
        "pair_age_days": 590,
        "token_age_days": null,
        "flags": []
      }
    },
    {
      "id": 36300,
      "symbol": "SKYAI",
      "name": "SKYAI",
      "price": 0.332553197552828,
      "market_cap": 332553197.552828,
      "volume_24h": 36459034.3995636,
      "pct_7d": 37.78961969,
      "pct_30d": -8.21849819,
      "float_ratio": 1,
      "score": 0.7084693465879801,
      "parts": {
        "float_quality": 1,
        "momentum_24h": 0,
        "momentum_7d": 0.7557923938000001,
        "momentum_30d": 0,
        "volume_surge": 0.21926738138653365
      },
      "dd": {
        "tvl": null,
        "category": "BNB Chain Ecosystem",
        "fees24h": null,
        "liquidity_usd": 13317564.12,
        "pair_age_days": 420,
        "token_age_days": null,
        "flags": []
      }
    },
    {
      "id": 7431,
      "symbol": "AKT",
      "name": "Akash Network",
      "price": 0.7301595513663731,
      "market_cap": 215231493.78723252,
      "volume_24h": 20941445.86998279,
      "pct_7d": 20.3173733,
      "pct_30d": -7.41204309,
      "float_ratio": 1,
      "score": 0.700793176993026,
      "parts": {
        "float_quality": 1,
        "momentum_24h": 0.41292315599999996,
        "momentum_7d": 0.406347466,
        "momentum_30d": 0,
        "volume_surge": 0.19459462462017288
      },
      "dd": {
        "tvl": null,
        "category": "Artificial Intelligence (AI)",
        "fees24h": null,
        "liquidity_usd": 523106227.95,
        "pair_age_days": 458,
        "token_age_days": null,
        "flags": []
      }
    },
    {
      "id": 25028,
      "symbol": "ORDI",
      "name": "ORDI",
      "price": 3.2964416676184025,
      "market_cap": 69225275.01998645,
      "volume_24h": 16674019.67536806,
      "pct_7d": 11.54505189,
      "pct_30d": -26.54845547,
      "float_ratio": 1,
      "score": 0.6953499236386601,
      "parts": {
        "float_quality": 1,
        "momentum_24h": 0,
        "momentum_7d": 0.2309010378,
        "momentum_30d": 0,
        "volume_surge": 0.48173213239106677
      },
      "dd": {
        "tvl": null,
        "category": null,
        "fees24h": null,
        "liquidity_usd": null,
        "pair_age_days": null,
        "token_age_days": null,
        "flags": []
      }
    },
    {
      "id": 33093,
      "symbol": "MOODENG",
      "name": "Moo Deng (moodengsol.com)",
      "price": 0.039581404719050486,
      "market_cap": 39184474.1267431,
      "volume_24h": 11062775.9190966,
      "pct_7d": 4.3247477,
      "pct_30d": -29.79443029,
      "float_ratio": 1,
      "score": 0.6933471428660383,
      "parts": {
        "float_quality": 1,
        "momentum_24h": 0,
        "momentum_7d": 0.086494954,
        "momentum_30d": 0,
        "volume_surge": 0.564650983106921
      },
      "dd": {
        "tvl": null,
        "category": null,
        "fees24h": null,
        "liquidity_usd": 2083396.83,
        "pair_age_days": 641,
        "token_age_days": null,
        "flags": []
      }
    },
    {
      "id": 8425,
      "symbol": "JASMY",
      "name": "JasmyCoin",
      "price": 0.005290653508032375,
      "market_cap": 261596360.9966769,
      "volume_24h": 41058872.22481918,
      "pct_7d": 11.34468096,
      "pct_30d": -16.65105134,
      "float_ratio": 0.9888999935433915,
      "score": 0.693302640814154,
      "parts": {
        "float_quality": 0.9888999935433915,
        "momentum_24h": 0.40249020166666666,
        "momentum_7d": 0.2268936192,
        "momentum_30d": 0,
        "volume_surge": 0.31391011762079335
      },
      "dd": {
        "tvl": null,
        "category": null,
        "fees24h": null,
        "liquidity_usd": null,
        "pair_age_days": null,
        "token_age_days": null,
        "flags": []
      }
    },
    {
      "id": 24911,
      "symbol": "TURBO",
      "name": "Turbo",
      "price": 0.0008902526733301492,
      "market_cap": 61427434.45087777,
      "volume_24h": 16723137.23030121,
      "pct_7d": 4.14150801,
      "pct_30d": -30.52636212,
      "float_ratio": 1,
      "score": 0.6924960096048308,
      "parts": {
        "float_quality": 1,
        "momentum_24h": 0.033871288000000006,
        "momentum_7d": 0.0828301602,
        "momentum_30d": 0,
        "volume_surge": 0.5444843132322041
      },
      "dd": {
        "tvl": null,
        "category": null,
        "fees24h": null,
        "liquidity_usd": null,
        "pair_age_days": null,
        "token_age_days": null,
        "flags": []
      }
    },
    {
      "id": 28782,
      "symbol": "POPCAT",
      "name": "Popcat (SOL)",
      "price": 0.04083291502321118,
      "market_cap": 40013664.910107724,
      "volume_24h": 11314485.66882858,
      "pct_7d": 1.08961663,
      "pct_30d": -33.98176035,
      "float_ratio": 1,
      "score": 0.6870088960333078,
      "parts": {
        "float_quality": 1,
        "momentum_24h": 0,
        "momentum_7d": 0.021792332600000002,
        "momentum_30d": 0,
        "volume_surge": 0.5655310851553847
      },
      "dd": {
        "tvl": null,
        "category": null,
        "fees24h": null,
        "liquidity_usd": 2639312.35,
        "pair_age_days": 914,
        "token_age_days": null,
        "flags": []
      }
    },
    {
      "id": 37006,
      "symbol": "SPYX",
      "name": "SP500 tokenized ETF (xStock)",
      "price": 747.7107764014022,
      "market_cap": 161848748.3741402,
      "volume_24h": 39588703.49281952,
      "pct_7d": 1.18925798,
      "pct_30d": 0.65787555,
      "float_ratio": 1,
      "score": 0.6768399629223726,
      "parts": {
        "float_quality": 1,
        "momentum_24h": 0.007828189000000001,
        "momentum_7d": 0.0237851596,
        "momentum_30d": 0.0065787555,
        "volume_surge": 0.48920617416581647
      },
      "dd": {
        "tvl": null,
        "category": null,
        "fees24h": null,
        "liquidity_usd": 558876.53,
        "pair_age_days": 346,
        "token_age_days": null,
        "flags": []
      }
    },
    {
      "id": 33881,
      "symbol": "BAN",
      "name": "Comedian",
      "price": 0.07437392793913203,
      "market_cap": 74371091.24314651,
      "volume_24h": 7745923.39233805,
      "pct_7d": 12.09394133,
      "pct_30d": -0.68346187,
      "float_ratio": 1,
      "score": 0.672941019136181,
      "parts": {
        "float_quality": 1,
        "momentum_24h": 0.23343244833333332,
        "momentum_7d": 0.24187882659999999,
        "momentum_30d": 0,
        "volume_surge": 0.20830468567453908
      },
      "dd": {
        "tvl": 0,
        "category": "Yield",
        "fees24h": null,
        "liquidity_usd": 2385451.78,
        "pair_age_days": 596,
        "token_age_days": null,
        "flags": []
      }
    },
    {
      "id": 36296,
      "symbol": "BANK",
      "name": "Lorenzo Protocol",
      "price": 0.04064835132508395,
      "market_cap": 47689423.60137694,
      "volume_24h": 6279480.51644468,
      "pct_7d": 24.80849529,
      "pct_30d": 1.51239603,
      "float_ratio": 0.9678462048267881,
      "score": 0.6721653029563476,
      "parts": {
        "float_quality": 0.9678462048267881,
        "momentum_24h": 0.016052607333333333,
        "momentum_7d": 0.4961699058,
        "momentum_30d": 0.0151239603,
        "volume_surge": 0.2633489793851638
      },
      "dd": {
        "tvl": 252796.70206574607,
        "category": "Reserve Currency",
        "fees24h": 0,
        "liquidity_usd": 711272.14,
        "pair_age_days": 410,
        "token_age_days": null,
        "flags": [
          {
            "k": "TVL sans revenu",
            "t": "warn"
          }
        ]
      }
    },
    {
      "id": 4066,
      "symbol": "CHZ",
      "name": "Chiliz",
      "price": 0.02536894353186097,
      "market_cap": 264164545.30106798,
      "volume_24h": 57831150.89629348,
      "pct_7d": 2.32656797,
      "pct_30d": -43.39519615,
      "float_ratio": 1,
      "score": 0.670329418308306,
      "parts": {
        "float_quality": 1,
        "momentum_24h": 0,
        "momentum_7d": 0.0465313594,
        "momentum_30d": 0,
        "volume_surge": 0.43784188245537187
      },
      "dd": {
        "tvl": null,
        "category": null,
        "fees24h": null,
        "liquidity_usd": null,
        "pair_age_days": null,
        "token_age_days": null,
        "flags": []
      }
    },
    {
      "id": 27750,
      "symbol": "TOSHI",
      "name": "Toshi",
      "price": 0.00013108054537939944,
      "market_cap": 55141571.40376525,
      "volume_24h": 9059710.6313157,
      "pct_7d": 7.20836107,
      "pct_30d": -30.27984999,
      "float_ratio": 0.9999509789200755,
      "score": 0.6696520702614639,
      "parts": {
        "float_quality": 0.9999509789200755,
        "momentum_24h": 0.07966707133333334,
        "momentum_7d": 0.1441672214,
        "momentum_30d": 0,
        "volume_surge": 0.3285982027961239
      },
      "dd": {
        "tvl": null,
        "category": null,
        "fees24h": null,
        "liquidity_usd": 420235.77,
        "pair_age_days": 315,
        "token_age_days": null,
        "flags": []
      }
    },
    {
      "id": 28752,
      "symbol": "WIF",
      "name": "dogwifhat",
      "price": 0.1573647317891298,
      "market_cap": 157182032.4669579,
      "volume_24h": 35801241.70925816,
      "pct_7d": 0.57629293,
      "pct_30d": -25.1114029,
      "float_ratio": 1,
      "score": 0.6694833762449331,
      "parts": {
        "float_quality": 1,
        "momentum_24h": 0,
        "momentum_7d": 0.011525858600000001,
        "momentum_30d": 0,
        "volume_surge": 0.45553860256622064
      },
      "dd": {
        "tvl": null,
        "category": null,
        "fees24h": null,
        "liquidity_usd": 4002667.62,
        "pair_age_days": 936,
        "token_age_days": null,
        "flags": []
      }
    },
    {
      "id": 36313,
      "symbol": "TROLL",
      "name": "TROLL (SOL)",
      "price": 0.08067627737900795,
      "market_cap": 80577191.15383954,
      "volume_24h": 3683839.39934103,
      "pct_7d": 17.0366226,
      "pct_30d": -29.98684439,
      "float_ratio": 1,
      "score": 0.6677880415476035,
      "parts": {
        "float_quality": 1,
        "momentum_24h": 0.2666580533333333,
        "momentum_7d": 0.340732452,
        "momentum_30d": 0,
        "volume_surge": 0.09143628231735634
      },
      "dd": {
        "tvl": null,
        "category": null,
        "fees24h": null,
        "liquidity_usd": 3136008.76,
        "pair_age_days": 419,
        "token_age_days": null,
        "flags": []
      }
    },
    {
      "id": 4846,
      "symbol": "KAVA",
      "name": "Kava",
      "price": 0.04533683733494714,
      "market_cap": 49092859.0230249,
      "volume_24h": 9263971.20895033,
      "pct_7d": 5.03423882,
      "pct_30d": -25.68369743,
      "float_ratio": 1,
      "score": 0.6666793863952151,
      "parts": {
        "float_quality": 1,
        "momentum_24h": 0,
        "momentum_7d": 0.1006847764,
        "momentum_30d": 0,
        "volume_surge": 0.37740605836810037
      },
      "dd": {
        "tvl": null,
        "category": null,
        "fees24h": null,
        "liquidity_usd": null,
        "pair_age_days": null,
        "token_age_days": null,
        "flags": []
      }
    },
    {
      "id": 10529,
      "symbol": "SUN",
      "name": "Sun [New]",
      "price": 0.01681334687884433,
      "market_cap": 323340954.4720299,
      "volume_24h": 65499662.59756344,
      "pct_7d": -4.95518411,
      "pct_30d": -14.30575946,
      "float_ratio": 1,
      "score": 0.660771450407062,
      "parts": {
        "float_quality": 1,
        "momentum_24h": 0,
        "momentum_7d": 0,
        "momentum_30d": 0,
        "volume_surge": 0.4051430027137461
      },
      "dd": {
        "tvl": 209183582.96941838,
        "category": "Dexs",
        "fees24h": 16071,
        "liquidity_usd": 16103672.72,
        "pair_age_days": 1641,
        "token_age_days": null,
        "flags": [
          {
            "k": "revenu réel",
            "t": "ok"
          }
        ]
      }
    },
    {
      "id": 38014,
      "symbol": "MUon",
      "name": "Micron Technology Tokenized Stock (Ondo)",
      "price": 999.8534851280002,
      "market_cap": 77357847.06572509,
      "volume_24h": 1979732.52537479,
      "pct_7d": 11.49026179,
      "pct_30d": 34.9456431,
      "float_ratio": 1,
      "score": 0.6601606541009066,
      "parts": {
        "float_quality": 1,
        "momentum_24h": 0.043911133666666664,
        "momentum_7d": 0.2298052358,
        "momentum_30d": 0.34945643099999996,
        "volume_surge": 0.051183754472710744
      },
      "dd": {
        "tvl": null,
        "category": null,
        "fees24h": null,
        "liquidity_usd": null,
        "pair_age_days": null,
        "token_age_days": null,
        "flags": []
      }
    },
    {
      "id": 27659,
      "symbol": "MOG",
      "name": "Mog Coin",
      "price": 1.0710369185166296e-7,
      "market_cap": 41831223.99836947,
      "volume_24h": 7736233.16254477,
      "pct_7d": 1.09417999,
      "pct_30d": -32.89872309,
      "float_ratio": 1,
      "score": 0.6576701204193766,
      "parts": {
        "float_quality": 1,
        "momentum_24h": 0,
        "momentum_7d": 0.0218835998,
        "momentum_30d": 0,
        "volume_surge": 0.3698784029291765
      },
      "dd": {
        "tvl": null,
        "category": null,
        "fees24h": null,
        "liquidity_usd": null,
        "pair_age_days": null,
        "token_age_days": null,
        "flags": []
      }
    },
    {
      "id": 12999,
      "symbol": "SSV",
      "name": "ssv.network",
      "price": 2.290408692954498,
      "market_cap": 37386834.55404045,
      "volume_24h": 7632693.23848087,
      "pct_7d": 13.17087727,
      "pct_30d": -18.65820613,
      "float_ratio": 0.940186748064232,
      "score": 0.6568567469326334,
      "parts": {
        "float_quality": 0.940186748064232,
        "momentum_24h": 0.06875428933333333,
        "momentum_7d": 0.2634175454,
        "momentum_30d": 0,
        "volume_surge": 0.4083091456939616
      },
      "dd": {
        "tvl": 12319043131.456457,
        "category": "Staking Pool",
        "fees24h": 8,
        "liquidity_usd": null,
        "pair_age_days": null,
        "token_age_days": null,
        "flags": [
          {
            "k": "TVL sans revenu",
            "t": "warn"
          }
        ]
      }
    },
    {
      "id": 5632,
      "symbol": "AR",
      "name": "Arweave",
      "price": 1.9805877485114438,
      "market_cap": 130030469.81916411,
      "volume_24h": 23790176.29110871,
      "pct_7d": 0.80614939,
      "pct_30d": -12.39520388,
      "float_ratio": 1,
      "score": 0.6564998408865406,
      "parts": {
        "float_quality": 1,
        "momentum_24h": 0,
        "momentum_7d": 0.0161229878,
        "momentum_30d": 0,
        "volume_surge": 0.3659169473769366
      },
      "dd": {
        "tvl": null,
        "category": null,
        "fees24h": null,
        "liquidity_usd": 490005205.23,
        "pair_age_days": 332,
        "token_age_days": null,
        "flags": []
      }
    },
    {
      "id": 35347,
      "symbol": "MELANIA",
      "name": "Official Melania Meme",
      "price": 0.07871269519701568,
      "market_cap": 78712378.86223376,
      "volume_24h": 9687374.54528962,
      "pct_7d": 8.98408762,
      "pct_30d": -23.80732903,
      "float_ratio": 0.9999999999999961,
      "score": 0.6548900978853988,
      "parts": {
        "float_quality": 0.9999999999999961,
        "momentum_24h": 0,
        "momentum_7d": 0.1796817524,
        "momentum_30d": 0,
        "volume_surge": 0.24614615096933953
      },
      "dd": {
        "tvl": 0,
        "category": "Meme",
        "fees24h": null,
        "liquidity_usd": 10421415.49,
        "pair_age_days": 510,
        "token_age_days": null,
        "flags": []
      }
    },
    {
      "id": 37041,
      "symbol": "HOODX",
      "name": "Robinhood tokenized stock (xStock)",
      "price": 93.98537914242088,
      "market_cap": 138130791.08460426,
      "volume_24h": 1534457.90512362,
      "pct_7d": 15.84874915,
      "pct_30d": 20.26280351,
      "float_ratio": 1,
      "score": 0.6527745401336934,
      "parts": {
        "float_quality": 1,
        "momentum_24h": 0.033964262333333335,
        "momentum_7d": 0.316974983,
        "momentum_30d": 0.20262803510000002,
        "volume_surge": 0.022217463507955646
      },
      "dd": {
        "tvl": null,
        "category": null,
        "fees24h": null,
        "liquidity_usd": null,
        "pair_age_days": null,
        "token_age_days": null,
        "flags": []
      }
    },
    {
      "id": 34926,
      "symbol": "ARC",
      "name": "AI Rig Complex",
      "price": 0.08328208032802722,
      "market_cap": 83281940.33085018,
      "volume_24h": 4557022.52916207,
      "pct_7d": 0.68712843,
      "pct_30d": 46.44224825,
      "float_ratio": 1,
      "score": 0.6526213477957274,
      "parts": {
        "float_quality": 1,
        "momentum_24h": 0,
        "momentum_7d": 0.0137425686,
        "momentum_30d": 0.4644224825,
        "volume_surge": 0.10943603165484868
      },
      "dd": {
        "tvl": 2679.3012278839296,
        "category": "Dexs",
        "fees24h": 0,
        "liquidity_usd": 3915895.15,
        "pair_age_days": 550,
        "token_age_days": null,
        "flags": [
          {
            "k": "TVL sans revenu",
            "t": "warn"
          }
        ]
      }
    },
    {
      "id": 2130,
      "symbol": "ENJ",
      "name": "Enjin Coin",
      "price": 0.0307396114325638,
      "market_cap": 60689968.17054524,
      "volume_24h": 11226637.35952643,
      "pct_7d": 1.73832682,
      "pct_30d": -32.33743081,
      "float_ratio": 0.9883908649438685,
      "score": 0.6520061960736844,
      "parts": {
        "float_quality": 0.9883908649438685,
        "momentum_24h": 0,
        "momentum_7d": 0.0347665364,
        "momentum_30d": 0,
        "volume_surge": 0.36996682311575413
      },
      "dd": {
        "tvl": null,
        "category": null,
        "fees24h": null,
        "liquidity_usd": 194316365.61,
        "pair_age_days": 419,
        "token_age_days": null,
        "flags": []
      }
    },
    {
      "id": 10180,
      "symbol": "GOMINING",
      "name": "GoМining",
      "price": 0.27879683256294946,
      "market_cap": 112708305.57265905,
      "volume_24h": 10701493.9553416,
      "pct_7d": 6.93104286,
      "pct_30d": -4.86282062,
      "float_ratio": 1,
      "score": 0.6504350919251235,
      "parts": {
        "float_quality": 1,
        "momentum_24h": 0.107845749,
        "momentum_7d": 0.1386208572,
        "momentum_30d": 0,
        "volume_surge": 0.18989716686748923
      },
      "dd": {
        "tvl": null,
        "category": null,
        "fees24h": null,
        "liquidity_usd": null,
        "pair_age_days": null,
        "token_age_days": null,
        "flags": []
      }
    },
    {
      "id": 26081,
      "symbol": "FDUSD",
      "name": "First Digital USD",
      "price": 0.997728697748152,
      "market_cap": 336749929.9750306,
      "volume_24h": 54666172.11191361,
      "pct_7d": 0.01704938,
      "pct_30d": -0.05255928,
      "float_ratio": 1,
      "score": 0.6487344849331764,
      "parts": {
        "float_quality": 1,
        "momentum_24h": 0,
        "momentum_7d": 0.0003409876,
        "momentum_30d": 0,
        "volume_surge": 0.32466924115450896
      },
      "dd": {
        "tvl": null,
        "category": null,
        "fees24h": null,
        "liquidity_usd": null,
        "pair_age_days": null,
        "token_age_days": null,
        "flags": []
      }
    },
    {
      "id": 3783,
      "symbol": "ANKR",
      "name": "Ankr",
      "price": 0.0039019265196555456,
      "market_cap": 39019265.19655546,
      "volume_24h": 5436489.81620516,
      "pct_7d": 1.30942478,
      "pct_30d": -21.07687225,
      "float_ratio": 1,
      "score": 0.6444173543920574,
      "parts": {
        "float_quality": 1,
        "momentum_24h": 0,
        "momentum_7d": 0.0261884956,
        "momentum_30d": 0,
        "volume_surge": 0.2786566988803819
      },
      "dd": {
        "tvl": 17691680.613135055,
        "category": "Liquid Staking",
        "fees24h": 1246,
        "liquidity_usd": null,
        "pair_age_days": null,
        "token_age_days": null,
        "flags": [
          {
            "k": "revenu réel",
            "t": "ok"
          }
        ]
      }
    },
    {
      "id": 36828,
      "symbol": "USELESS",
      "name": "Useless Coin",
      "price": 0.06580117890465717,
      "market_cap": 65740968.811956204,
      "volume_24h": 8127949.26156569,
      "pct_7d": 1.70028132,
      "pct_30d": 3.21823992,
      "float_ratio": 1,
      "score": 0.6429050372934823,
      "parts": {
        "float_quality": 1,
        "momentum_24h": 0,
        "momentum_7d": 0.0340056264,
        "momentum_30d": 0.032182399199999996,
        "volume_surge": 0.24727196475654836
      },
      "dd": {
        "tvl": null,
        "category": null,
        "fees24h": null,
        "liquidity_usd": 1847309.92,
        "pair_age_days": 399,
        "token_age_days": null,
        "flags": []
      }
    },
    {
      "id": 27048,
      "symbol": "APEPE",
      "name": "Ape and Pepe",
      "price": 0.0000010777010594035625,
      "market_cap": 226317222.47474813,
      "volume_24h": 26096222.38053035,
      "pct_7d": 3.23594866,
      "pct_30d": -9.30739018,
      "float_ratio": 1,
      "score": 0.6410643451618016,
      "parts": {
        "float_quality": 1,
        "momentum_24h": 0,
        "momentum_7d": 0.0647189732,
        "momentum_30d": 0,
        "volume_surge": 0.23061631894534315
      },
      "dd": {
        "tvl": null,
        "category": null,
        "fees24h": null,
        "liquidity_usd": 13653.36,
        "pair_age_days": 1102,
        "token_age_days": null,
        "flags": [
          {
            "k": "liquidité faible",
            "t": "bad"
          }
        ]
      }
    },
    {
      "id": 23121,
      "symbol": "BLUR",
      "name": "Blur",
      "price": 0.01789932535478371,
      "market_cap": 50492103.18551732,
      "volume_24h": 11171939.48577559,
      "pct_7d": 5.21891681,
      "pct_30d": -28.35373837,
      "float_ratio": 0.9402980686834095,
      "score": 0.6409950119220529,
      "parts": {
        "float_quality": 0.9402980686834095,
        "momentum_24h": 0,
        "momentum_7d": 0.10437833619999999,
        "momentum_30d": 0,
        "volume_surge": 0.44252224728004774
      },
      "dd": {
        "tvl": 13396622.466403661,
        "category": "NFT Marketplace",
        "fees24h": 0,
        "liquidity_usd": null,
        "pair_age_days": null,
        "token_age_days": null,
        "flags": [
          {
            "k": "TVL sans revenu",
            "t": "warn"
          }
        ]
      }
    },
    {
      "id": 131,
      "symbol": "DASH",
      "name": "Dash",
      "price": 35.18744456899712,
      "market_cap": 447976798.89086807,
      "volume_24h": 59619134.41093726,
      "pct_7d": -6.44075095,
      "pct_30d": -21.15271019,
      "float_ratio": 1,
      "score": 0.6399255951816344,
      "parts": {
        "float_quality": 1,
        "momentum_24h": 0,
        "momentum_7d": 0,
        "momentum_30d": 0,
        "volume_surge": 0.26617063454422835
      },
      "dd": {
        "tvl": null,
        "category": null,
        "fees24h": null,
        "liquidity_usd": 1030857910.74,
        "pair_age_days": 41,
        "token_age_days": null,
        "flags": []
      }
    },
    {
      "id": 38186,
      "symbol": "DIEM",
      "name": "Diem",
      "price": 1537.4846018309909,
      "market_cap": 59064511.90055722,
      "volume_24h": 1083607.03726635,
      "pct_7d": 7.76771403,
      "pct_30d": 23.17606525,
      "float_ratio": 1.0267508995469152,
      "score": 0.6384213252596718,
      "parts": {
        "float_quality": 1,
        "momentum_24h": 0,
        "momentum_7d": 0.1553542806,
        "momentum_30d": 0.2317606525,
        "volume_surge": 0.03669232174781172
      },
      "dd": {
        "tvl": 6.848113265880056,
        "category": "Yield",
        "fees24h": null,
        "liquidity_usd": 6524133.41,
        "pair_age_days": 297,
        "token_age_days": null,
        "flags": [
          {
            "k": "TVL sans revenu",
            "t": "warn"
          }
        ]
      }
    },
    {
      "id": 2566,
      "symbol": "ONT",
      "name": "Ontology",
      "price": 0.0480412106749655,
      "market_cap": 48041210.6749655,
      "volume_24h": 4814398.48645918,
      "pct_7d": 3.94883003,
      "pct_30d": -20.82776315,
      "float_ratio": 1,
      "score": 0.6379618388274682,
      "parts": {
        "float_quality": 1,
        "momentum_24h": 0,
        "momentum_7d": 0.0789766006,
        "momentum_30d": 0,
        "volume_surge": 0.20042785844978653
      },
      "dd": {
        "tvl": null,
        "category": null,
        "fees24h": null,
        "liquidity_usd": 103081664.36,
        "pair_age_days": 243,
        "token_age_days": null,
        "flags": []
      }
    },
    {
      "id": 10603,
      "symbol": "IMX",
      "name": "Immutable",
      "price": 0.14290742740856655,
      "market_cap": 285814854.8171331,
      "volume_24h": 11758284.27070976,
      "pct_7d": 12.33572603,
      "pct_30d": -29.46804972,
      "float_ratio": 1,
      "score": 0.6370133063120117,
      "parts": {
        "float_quality": 1,
        "momentum_24h": 0,
        "momentum_7d": 0.2467145206,
        "momentum_30d": 0,
        "volume_surge": 0.08227902834674436
      },
      "dd": {
        "tvl": 25265234.523364503,
        "category": "Chain",
        "fees24h": 13,
        "liquidity_usd": null,
        "pair_age_days": null,
        "token_age_days": null,
        "flags": [
          {
            "k": "TVL sans revenu",
            "t": "warn"
          }
        ]
      }
    },
    {
      "id": 33597,
      "symbol": "FARTCOIN",
      "name": "Fartcoin",
      "price": 0.1172884527793799,
      "market_cap": 117288248.22831826,
      "volume_24h": 9309657.42156647,
      "pct_7d": 6.41385149,
      "pct_30d": -44.07118308,
      "float_ratio": 0.999998256,
      "score": 0.636638907753137,
      "parts": {
        "float_quality": 0.999998256,
        "momentum_24h": 0,
        "momentum_7d": 0.1282770298,
        "momentum_30d": 0,
        "volume_surge": 0.15874834115424585
      },
      "dd": {
        "tvl": null,
        "category": null,
        "fees24h": null,
        "liquidity_usd": 5231704.79,
        "pair_age_days": 604,
        "token_age_days": null,
        "flags": []
      }
    },
    {
      "id": 12885,
      "symbol": "ASTR",
      "name": "Astar",
      "price": 0.005897559497203162,
      "market_cap": 51368938.60287159,
      "volume_24h": 2888631.2010459,
      "pct_7d": 5.30519991,
      "pct_30d": -34.24149027,
      "float_ratio": 0.9999106639069364,
      "score": 0.6340200893806274,
      "parts": {
        "float_quality": 0.9999106639069364,
        "momentum_24h": 0.08791175233333333,
        "momentum_7d": 0.1061039982,
        "momentum_30d": 0,
        "volume_surge": 0.11246606527643621
      },
      "dd": {
        "tvl": 17673348.905784648,
        "category": "Chain",
        "fees24h": null,
        "liquidity_usd": null,
        "pair_age_days": null,
        "token_age_days": null,
        "flags": [
          {
            "k": "TVL sans revenu",
            "t": "warn"
          }
        ]
      }
    },
    {
      "id": 4558,
      "symbol": "FLOW",
      "name": "Flow",
      "price": 0.028294839614867128,
      "market_cap": 47200517.093971126,
      "volume_24h": 3104475.98324024,
      "pct_7d": 7.0059119,
      "pct_30d": -24.3870221,
      "float_ratio": 1,
      "score": 0.6337434465090875,
      "parts": {
        "float_quality": 1,
        "momentum_24h": 0,
        "momentum_7d": 0.140118238,
        "momentum_30d": 0,
        "volume_surge": 0.13154415139391645
      },
      "dd": {
        "tvl": 29128.185038553784,
        "category": "Dexs",
        "fees24h": null,
        "liquidity_usd": 596632059.17,
        "pair_age_days": 249,
        "token_age_days": null,
        "flags": [
          {
            "k": "TVL sans revenu",
            "t": "warn"
          }
        ]
      }
    },
    {
      "id": 1684,
      "symbol": "QTUM",
      "name": "Qtum",
      "price": 0.727870375866655,
      "market_cap": 77187085.88597904,
      "volume_24h": 8967872.51737708,
      "pct_7d": 3.91905176,
      "pct_30d": -23.5654627,
      "float_ratio": 0.9835163458511582,
      "score": 0.6328029871659352,
      "parts": {
        "float_quality": 0.9835163458511582,
        "momentum_24h": 0,
        "momentum_7d": 0.0783810352,
        "momentum_30d": 0,
        "volume_surge": 0.2323671742349347
      },
      "dd": {
        "tvl": null,
        "category": null,
        "fees24h": null,
        "liquidity_usd": 255395908.41,
        "pair_age_days": 248,
        "token_age_days": null,
        "flags": []
      }
    },
    {
      "id": 37545,
      "symbol": "BNKR",
      "name": "BankrCoin",
      "price": 0.0004821162167847601,
      "market_cap": 47874140.32672652,
      "volume_24h": 5452034.06578621,
      "pct_7d": -14.30707795,
      "pct_30d": -5.2937733,
      "float_ratio": 0.9929999999999967,
      "score": 0.6299647956197904,
      "parts": {
        "float_quality": 0.9929999999999967,
        "momentum_24h": 0,
        "momentum_7d": 0,
        "momentum_30d": 0,
        "volume_surge": 0.22776530413194795
      },
      "dd": {
        "tvl": 0,
        "category": "Interface",
        "fees24h": 52190,
        "liquidity_usd": 2212337.45,
        "pair_age_days": 558,
        "token_age_days": null,
        "flags": [
          {
            "k": "revenu réel",
            "t": "ok"
          }
        ]
      }
    },
    {
      "id": 2765,
      "symbol": "XYO",
      "name": "XYO",
      "price": 0.0035459967455524315,
      "market_cap": 48941432.87602642,
      "volume_24h": 5723881.60928066,
      "pct_7d": -0.61135255,
      "pct_30d": -11.57614437,
      "float_ratio": 0.9907492663084095,
      "score": 0.6295356694854697,
      "parts": {
        "float_quality": 0.9907492663084095,
        "momentum_24h": 0,
        "momentum_7d": 0,
        "momentum_30d": 0,
        "volume_surge": 0.23390739800282628
      },
      "dd": {
        "tvl": null,
        "category": null,
        "fees24h": null,
        "liquidity_usd": null,
        "pair_age_days": null,
        "token_age_days": null,
        "flags": []
      }
    }
  ]
}