{
  "updated_at": "2026-07-12T12:54:54.028Z",
  "source": "coinmarketcap",
  "note": "Triage, pas un prédicteur. Le tracker dit si le score vaut quelque chose.",
  "weights_mode": "appris",
  "weights": {
    "float_quality": 0.382,
    "momentum_24h": 0.075,
    "momentum_7d": 0.1,
    "momentum_30d": 0.075,
    "volume_surge": 0.368
  },
  "dd_status": {
    "coingecko": true,
    "cg": 0,
    "dd": 36
  },
  "count": 50,
  "candidates": [
    {
      "id": 17751,
      "symbol": "T",
      "name": "Threshold",
      "price": 0.005614484470377832,
      "market_cap": 62629574.26706471,
      "volume_24h": 148807302.84031242,
      "pct_7d": 60.17259615,
      "pct_30d": 47.76488373,
      "float_ratio": 1,
      "score": 0.9536055749725,
      "parts": {
        "float_quality": 1,
        "momentum_24h": 0.9037588289999999,
        "momentum_7d": 1,
        "momentum_30d": 0.4776488373,
        "volume_surge": 1
      },
      "dd": {
        "tvl": 330047385.74710745,
        "category": "Decentralized BTC",
        "fees24h": 1745,
        "liquidity_usd": null,
        "pair_age_days": null,
        "token_age_days": null,
        "flags": [
          {
            "k": "revenu réel",
            "t": "ok"
          }
        ]
      }
    },
    {
      "id": 40809,
      "symbol": "CASHCAT",
      "name": "Cash Cat",
      "price": 0.1784320803123327,
      "market_cap": 178432080.3123327,
      "volume_24h": 50702848.7429574,
      "pct_7d": 4175.48581727,
      "pct_30d": 22227.83349155,
      "float_ratio": 1,
      "score": 0.7661400638803031,
      "parts": {
        "float_quality": 1,
        "momentum_24h": 0,
        "momentum_7d": 1,
        "momentum_30d": 1,
        "volume_surge": 0.5683153909790847
      },
      "dd": {
        "tvl": null,
        "category": "Meme",
        "fees24h": null,
        "liquidity_usd": null,
        "pair_age_days": null,
        "token_age_days": null,
        "flags": []
      }
    },
    {
      "id": 23121,
      "symbol": "BLUR",
      "name": "Blur",
      "price": 0.01712051407387607,
      "market_cap": 48643597.292394064,
      "volume_24h": 25150693.62904299,
      "pct_7d": 14.57569923,
      "pct_30d": -7.40300074,
      "float_ratio": 0.9470821005041857,
      "score": 0.758936760852599,
      "parts": {
        "float_quality": 0.9470821005041857,
        "momentum_24h": 0,
        "momentum_7d": 0.2915139846,
        "momentum_30d": 0,
        "volume_surge": 1
      },
      "dd": {
        "tvl": 13571728.04996295,
        "category": "NFT Marketplace",
        "fees24h": 0,
        "liquidity_usd": null,
        "pair_age_days": null,
        "token_age_days": null,
        "flags": [
          {
            "k": "TVL sans revenu",
            "t": "warn"
          }
        ]
      }
    },
    {
      "id": 3783,
      "symbol": "ANKR",
      "name": "Ankr",
      "price": 0.0037140806180063655,
      "market_cap": 37140806.18006366,
      "volume_24h": 53932517.74222105,
      "pct_7d": 2.25269991,
      "pct_30d": -4.24917312,
      "float_ratio": 1,
      "score": 0.75450539982,
      "parts": {
        "float_quality": 1,
        "momentum_24h": 0,
        "momentum_7d": 0.0450539982,
        "momentum_30d": 0,
        "volume_surge": 1
      },
      "dd": {
        "tvl": 19481595.31227877,
        "category": "Liquid Staking",
        "fees24h": 1361,
        "liquidity_usd": null,
        "pair_age_days": null,
        "token_age_days": null,
        "flags": [
          {
            "k": "revenu réel",
            "t": "ok"
          }
        ]
      }
    },
    {
      "id": 36532,
      "symbol": "B",
      "name": "BUILDon",
      "price": 0.11578229314277556,
      "market_cap": 115782293.14277557,
      "volume_24h": 74776841.495548,
      "pct_7d": -45.43646958,
      "pct_30d": -50.69850652,
      "float_ratio": 1,
      "score": 0.75,
      "parts": {
        "float_quality": 1,
        "momentum_24h": 0,
        "momentum_7d": 0,
        "momentum_30d": 0,
        "volume_surge": 1
      },
      "dd": {
        "tvl": 1712109.7400585231,
        "category": "Liquidity Manager",
        "fees24h": null,
        "liquidity_usd": 1812614.7,
        "pair_age_days": 465,
        "token_age_days": null,
        "flags": [
          {
            "k": "TVL sans revenu",
            "t": "warn"
          }
        ]
      }
    },
    {
      "id": 33093,
      "symbol": "MOODENG",
      "name": "Moo Deng (moodengsol.com)",
      "price": 0.03999966868202469,
      "market_cap": 39598543.651350535,
      "volume_24h": 21792623.23669855,
      "pct_7d": -5.16538517,
      "pct_30d": -1.50827217,
      "float_ratio": 1,
      "score": 0.75,
      "parts": {
        "float_quality": 1,
        "momentum_24h": 0,
        "momentum_7d": 0,
        "momentum_30d": 0,
        "volume_surge": 1
      },
      "dd": {
        "tvl": null,
        "category": "Solana Ecosystem",
        "fees24h": null,
        "liquidity_usd": 2240861.17,
        "pair_age_days": 669,
        "token_age_days": null,
        "flags": []
      }
    },
    {
      "id": 24911,
      "symbol": "TURBO",
      "name": "Turbo",
      "price": 0.0008450534117196239,
      "market_cap": 58308685.40020352,
      "volume_24h": 25316116.28769106,
      "pct_7d": -6.76683079,
      "pct_30d": -2.8238311,
      "float_ratio": 1,
      "score": 0.7015520780455734,
      "parts": {
        "float_quality": 1,
        "momentum_24h": 0,
        "momentum_7d": 0,
        "momentum_30d": 0,
        "volume_surge": 0.868348038167319
      },
      "dd": {
        "tvl": null,
        "category": "Meme",
        "fees24h": null,
        "liquidity_usd": null,
        "pair_age_days": null,
        "token_age_days": null,
        "flags": []
      }
    },
    {
      "id": 12147,
      "symbol": "SYN",
      "name": "Synapse",
      "price": 0.3215752365995777,
      "market_cap": 75624203.14988737,
      "volume_24h": 24658174.54176949,
      "pct_7d": -19.34151411,
      "pct_30d": 924.03025943,
      "float_ratio": 0.9445102296210373,
      "score": 0.6913043313572454,
      "parts": {
        "float_quality": 0.9445102296210373,
        "momentum_24h": 0.20693112433333333,
        "momentum_7d": 0,
        "momentum_30d": 1,
        "volume_surge": 0.652123884013612
      },
      "dd": {
        "tvl": 11600771.202295749,
        "category": "Cross Chain Bridge",
        "fees24h": 16,
        "liquidity_usd": null,
        "pair_age_days": null,
        "token_age_days": null,
        "flags": [
          {
            "k": "TVL sans revenu",
            "t": "warn"
          }
        ]
      }
    },
    {
      "id": 10407,
      "symbol": "BabyDoge",
      "name": "Baby Doge Coin",
      "price": 3.206848490583684e-10,
      "market_cap": 57462242.87942996,
      "volume_24h": 23553994.02706405,
      "pct_7d": 4.90064604,
      "pct_30d": -4.28876602,
      "float_ratio": 0.8843667229689597,
      "score": 0.6493186066961704,
      "parts": {
        "float_quality": 0.8843667229689597,
        "momentum_24h": 0,
        "momentum_7d": 0.0980129208,
        "momentum_30d": 0,
        "volume_surge": 0.8198076805489884
      },
      "dd": {
        "tvl": 1899078.3979862982,
        "category": "Dexs",
        "fees24h": 111,
        "liquidity_usd": null,
        "pair_age_days": null,
        "token_age_days": null,
        "flags": [
          {
            "k": "TVL sans revenu",
            "t": "warn"
          }
        ]
      }
    },
    {
      "id": 26081,
      "symbol": "FDUSD",
      "name": "First Digital USD",
      "price": 0.9968605791090785,
      "market_cap": 347062525.03326446,
      "volume_24h": 118799168.85356954,
      "pct_7d": -0.08515687,
      "pct_30d": -0.06405433,
      "float_ratio": 1,
      "score": 0.6339320928349922,
      "parts": {
        "float_quality": 1,
        "momentum_24h": 0,
        "momentum_7d": 0,
        "momentum_30d": 0,
        "volume_surge": 0.684598078355957
      },
      "dd": {
        "tvl": null,
        "category": "Stablecoins",
        "fees24h": null,
        "liquidity_usd": null,
        "pair_age_days": null,
        "token_age_days": null,
        "flags": []
      }
    },
    {
      "id": 2943,
      "symbol": "RPL",
      "name": "Rocket Pool",
      "price": 1.8384146014646279,
      "market_cap": 41584197.7832111,
      "volume_24h": 11858863.73879971,
      "pct_7d": -7.36956033,
      "pct_30d": 33.76716482,
      "float_ratio": 1,
      "score": 0.630977667159359,
      "parts": {
        "float_quality": 1,
        "momentum_24h": 0.18349197633333333,
        "momentum_7d": 0,
        "momentum_30d": 0.33767164819999995,
        "volume_surge": 0.5703543351069537
      },
      "dd": {
        "tvl": 952981618.5384452,
        "category": "Liquid Staking",
        "fees24h": 1636,
        "liquidity_usd": null,
        "pair_age_days": null,
        "token_age_days": null,
        "flags": [
          {
            "k": "revenu réel",
            "t": "ok"
          }
        ]
      }
    },
    {
      "id": 29743,
      "symbol": "BRETT",
      "name": "Brett (Based)",
      "price": 0.005349528482548936,
      "market_cap": 53495271.69091588,
      "volume_24h": 17813596.56941764,
      "pct_7d": -2.55227311,
      "pct_30d": -7.40816978,
      "float_ratio": 1,
      "score": 0.6270834748693828,
      "parts": {
        "float_quality": 1,
        "momentum_24h": 0,
        "momentum_7d": 0,
        "momentum_30d": 0,
        "volume_surge": 0.6659877034494096
      },
      "dd": {
        "tvl": null,
        "category": "BNB Chain Ecosystem",
        "fees24h": null,
        "liquidity_usd": null,
        "pair_age_days": null,
        "token_age_days": null,
        "flags": []
      }
    },
    {
      "id": 8536,
      "symbol": "MASK",
      "name": "Mask Network",
      "price": 0.4132362454365038,
      "market_cap": 41323624.54365038,
      "volume_24h": 12299061.20926801,
      "pct_7d": -4.39391419,
      "pct_30d": 14.34128361,
      "float_ratio": 1,
      "score": 0.6185466992211067,
      "parts": {
        "float_quality": 1,
        "momentum_24h": 0.08982192766666668,
        "momentum_7d": 0,
        "momentum_30d": 0.1434128361,
        "volume_surge": 0.595255684615779
      },
      "dd": {
        "tvl": null,
        "category": null,
        "fees24h": null,
        "liquidity_usd": null,
        "pair_age_days": null,
        "token_age_days": null,
        "flags": []
      }
    },
    {
      "id": 29587,
      "symbol": "W",
      "name": "Wormhole",
      "price": 0.009687008134687492,
      "market_cap": 59703526.17801623,
      "volume_24h": 79812673.71935885,
      "pct_7d": -3.57115191,
      "pct_30d": 3.55458595,
      "float_ratio": 0.6163257566,
      "score": 0.6061023784837,
      "parts": {
        "float_quality": 0.6163257566,
        "momentum_24h": 0,
        "momentum_7d": 0,
        "momentum_30d": 0.0355458595,
        "volume_surge": 1
      },
      "dd": {
        "tvl": 2556074916.814182,
        "category": "Bridge",
        "fees24h": 280,
        "liquidity_usd": null,
        "pair_age_days": null,
        "token_age_days": null,
        "flags": [
          {
            "k": "TVL sans revenu",
            "t": "warn"
          }
        ]
      }
    },
    {
      "id": 36195,
      "symbol": "AGT",
      "name": "Alaya Governance Token",
      "price": 0.012917122849945286,
      "market_cap": 37645791.152578935,
      "volume_24h": 20893279.20747943,
      "pct_7d": 4.92004282,
      "pct_30d": -8.96401808,
      "float_ratio": 0.5828819868,
      "score": 0.6018212576976,
      "parts": {
        "float_quality": 0.5828819868,
        "momentum_24h": 0.017603374666666668,
        "momentum_7d": 0.0984008564,
        "momentum_30d": 0,
        "volume_surge": 1
      },
      "dd": {
        "tvl": 0,
        "category": "Decentralized AI",
        "fees24h": null,
        "liquidity_usd": null,
        "pair_age_days": null,
        "token_age_days": null,
        "flags": []
      }
    },
    {
      "id": 32197,
      "symbol": "ME",
      "name": "Magic Eden",
      "price": 0.0639505696189929,
      "market_cap": 37235840.73826647,
      "volume_24h": 122165320.73818892,
      "pct_7d": 2.12272707,
      "pct_30d": 4.13129914,
      "float_ratio": 0.582265056227536,
      "score": 0.5977691799739188,
      "parts": {
        "float_quality": 0.582265056227536,
        "momentum_24h": 0,
        "momentum_7d": 0.0424545414,
        "momentum_30d": 0.041312991400000006,
        "volume_surge": 1
      },
      "dd": {
        "tvl": 117498.76064688199,
        "category": "NFT Marketplace",
        "fees24h": null,
        "liquidity_usd": 627808.5,
        "pair_age_days": 578,
        "token_age_days": null,
        "flags": [
          {
            "k": "TVL sans revenu",
            "t": "warn"
          }
        ]
      }
    },
    {
      "id": 4944,
      "symbol": "TRB",
      "name": "Tellor",
      "price": 15.19955943114835,
      "market_cap": 42438629.089471586,
      "volume_24h": 11841306.05652121,
      "pct_7d": -4.09878701,
      "pct_30d": 13.19311492,
      "float_ratio": 0.971056418803068,
      "score": 0.5861984915640883,
      "parts": {
        "float_quality": 0.971056418803068,
        "momentum_24h": 0,
        "momentum_7d": 0,
        "momentum_30d": 0.1319311492,
        "volume_surge": 0.5580437592155336
      },
      "dd": {
        "tvl": null,
        "category": null,
        "fees24h": null,
        "liquidity_usd": null,
        "pair_age_days": null,
        "token_age_days": null,
        "flags": []
      }
    },
    {
      "id": 28782,
      "symbol": "POPCAT",
      "name": "Popcat (SOL)",
      "price": 0.04536779015506792,
      "market_cap": 44457546.8343786,
      "volume_24h": 11168488.64938761,
      "pct_7d": -11.34652092,
      "pct_30d": 9.64660177,
      "float_ratio": 1,
      "score": 0.5741306154218766,
      "parts": {
        "float_quality": 1,
        "momentum_24h": 0,
        "momentum_7d": 0,
        "momentum_30d": 0.0964660177,
        "volume_surge": 0.5024338698216755
      },
      "dd": {
        "tvl": null,
        "category": null,
        "fees24h": null,
        "liquidity_usd": 2996160.43,
        "pair_age_days": 942,
        "token_age_days": null,
        "flags": []
      }
    },
    {
      "id": 3773,
      "symbol": "FET",
      "name": "Artificial Superintelligence Alliance",
      "price": 0.16029408448203802,
      "market_cap": 360250612.5738157,
      "volume_24h": 125240925.49965768,
      "pct_7d": -8.70398979,
      "pct_30d": -15.82500215,
      "float_ratio": 0.8279723969008798,
      "score": 0.5721554470900876,
      "parts": {
        "float_quality": 0.8279723969008798,
        "momentum_24h": 0,
        "momentum_7d": 0,
        "momentum_30d": 0,
        "volume_surge": 0.6952988898748683
      },
      "dd": {
        "tvl": null,
        "category": null,
        "fees24h": null,
        "liquidity_usd": 2086927012.69,
        "pair_age_days": 441,
        "token_age_days": null,
        "flags": []
      }
    },
    {
      "id": 28752,
      "symbol": "WIF",
      "name": "dogwifhat",
      "price": 0.15053599726927594,
      "market_cap": 150361221.7530089,
      "volume_24h": 38015082.99103039,
      "pct_7d": -13.52008046,
      "pct_30d": -5.41563362,
      "float_ratio": 1,
      "score": 0.5680792347601317,
      "parts": {
        "float_quality": 1,
        "momentum_24h": 0,
        "momentum_7d": 0,
        "momentum_30d": 0,
        "volume_surge": 0.5056500944568796
      },
      "dd": {
        "tvl": null,
        "category": null,
        "fees24h": null,
        "liquidity_usd": 4194099.48,
        "pair_age_days": 964,
        "token_age_days": null,
        "flags": []
      }
    },
    {
      "id": 3701,
      "symbol": "RIF",
      "name": "Rootstock Infrastructure Framework",
      "price": 0.13489003354553425,
      "market_cap": 134890033.54553425,
      "volume_24h": 9081027.50571318,
      "pct_7d": 20.1789866,
      "pct_30d": 101.94586624,
      "float_ratio": 1,
      "score": 0.5605715582144631,
      "parts": {
        "float_quality": 1,
        "momentum_24h": 0.182197435,
        "momentum_7d": 0.403579732,
        "momentum_30d": 1,
        "volume_surge": 0.13464341681919348
      },
      "dd": {
        "tvl": null,
        "category": null,
        "fees24h": null,
        "liquidity_usd": null,
        "pair_age_days": null,
        "token_age_days": null,
        "flags": []
      }
    },
    {
      "id": 1757,
      "symbol": "FUN",
      "name": "FUNToken",
      "price": 0.0035413932776351075,
      "market_cap": 38269009.90982012,
      "volume_24h": 3573432.99846445,
      "pct_7d": 18.15266804,
      "pct_30d": 65.45182994,
      "float_ratio": 1,
      "score": 0.5464094163609812,
      "parts": {
        "float_quality": 1,
        "momentum_24h": 0.137199642,
        "momentum_7d": 0.36305336079999995,
        "momentum_30d": 0.6545182994,
        "volume_surge": 0.1867533550977748
      },
      "dd": {
        "tvl": 0.19815361750000002,
        "category": "Dexs",
        "fees24h": null,
        "liquidity_usd": null,
        "pair_age_days": null,
        "token_age_days": null,
        "flags": [
          {
            "k": "TVL sans revenu",
            "t": "warn"
          }
        ]
      }
    },
    {
      "id": 27659,
      "symbol": "MOG",
      "name": "Mog Coin",
      "price": 1.0421013142829184e-7,
      "market_cap": 40701093.26122836,
      "volume_24h": 9003549.79246481,
      "pct_7d": -9.41350305,
      "pct_30d": -5.18997831,
      "float_ratio": 1,
      "score": 0.5448116622008916,
      "parts": {
        "float_quality": 1,
        "momentum_24h": 0,
        "momentum_7d": 0,
        "momentum_30d": 0,
        "volume_surge": 0.44242299511111866
      },
      "dd": {
        "tvl": null,
        "category": null,
        "fees24h": null,
        "liquidity_usd": 4486112.9,
        "pair_age_days": 1088,
        "token_age_days": null,
        "flags": []
      }
    },
    {
      "id": 7080,
      "symbol": "GALA",
      "name": "Gala",
      "price": 0.0020870691191728916,
      "market_cap": 101724692.45181999,
      "volume_24h": 22435194.89264834,
      "pct_7d": -9.48371306,
      "pct_30d": -21.62077976,
      "float_ratio": 1,
      "score": 0.5443234540503519,
      "parts": {
        "float_quality": 1,
        "momentum_24h": 0,
        "momentum_7d": 0,
        "momentum_30d": 0,
        "volume_surge": 0.44109634252813007
      },
      "dd": {
        "tvl": null,
        "category": null,
        "fees24h": null,
        "liquidity_usd": null,
        "pair_age_days": null,
        "token_age_days": null,
        "flags": []
      }
    },
    {
      "id": 2682,
      "symbol": "HOT",
      "name": "Holo",
      "price": 0.00036320238693728416,
      "market_cap": 64078325.607683584,
      "volume_24h": 12971839.21233483,
      "pct_7d": -8.40005668,
      "pct_30d": 16.4925058,
      "float_ratio": 0.9932806617404475,
      "score": 0.541407255600887,
      "parts": {
        "float_quality": 0.9932806617404475,
        "momentum_24h": 0.008144756666666666,
        "momentum_7d": 0,
        "momentum_30d": 0.164925058,
        "volume_surge": 0.40487447477183724
      },
      "dd": {
        "tvl": null,
        "category": null,
        "fees24h": null,
        "liquidity_usd": null,
        "pair_age_days": null,
        "token_age_days": null,
        "flags": []
      }
    },
    {
      "id": 17799,
      "symbol": "AXL",
      "name": "Axelar",
      "price": 0.042908057871422337,
      "market_cap": 51577403.99825962,
      "volume_24h": 11823690.72744193,
      "pct_7d": -0.33005249,
      "pct_30d": -0.24584719,
      "float_ratio": 0.9638300435122783,
      "score": 0.539769279685391,
      "parts": {
        "float_quality": 0.9638300435122783,
        "momentum_24h": 0.038191024,
        "momentum_7d": 0,
        "momentum_30d": 0,
        "volume_surge": 0.4584833594122301
      },
      "dd": {
        "tvl": 135187461.5653311,
        "category": "Bridge",
        "fees24h": 60,
        "liquidity_usd": null,
        "pair_age_days": null,
        "token_age_days": null,
        "flags": [
          {
            "k": "TVL sans revenu",
            "t": "warn"
          }
        ]
      }
    },
    {
      "id": 1974,
      "symbol": "PRO",
      "name": "Propy",
      "price": 0.3757374555690795,
      "market_cap": 37573745.55690795,
      "volume_24h": 6457724.12486137,
      "pct_7d": 0.00816286,
      "pct_30d": 23.81198247,
      "float_ratio": 1,
      "score": 0.5380594124473028,
      "parts": {
        "float_quality": 1,
        "momentum_24h": 0.15585679,
        "momentum_7d": 0.00016325719999999997,
        "momentum_30d": 0.2381198247,
        "volume_surge": 0.3437359799587036
      },
      "dd": {
        "tvl": null,
        "category": null,
        "fees24h": null,
        "liquidity_usd": null,
        "pair_age_days": null,
        "token_age_days": null,
        "flags": []
      }
    },
    {
      "id": 36056,
      "symbol": "XP",
      "name": "Xphere",
      "price": 0.02015574042055576,
      "market_cap": 57189503.49137815,
      "volume_24h": 1019108.89334206,
      "pct_7d": 47.34656955,
      "pct_30d": -25.13076975,
      "float_ratio": 1,
      "score": 0.5325532572613616,
      "parts": {
        "float_quality": 1,
        "momentum_24h": 0.5699293583333334,
        "momentum_7d": 0.946931391,
        "momentum_30d": 0,
        "volume_surge": 0.035639718169460946
      },
      "dd": {
        "tvl": null,
        "category": null,
        "fees24h": null,
        "liquidity_usd": 15823.58,
        "pair_age_days": 27,
        "token_age_days": null,
        "flags": [
          {
            "k": "liquidité faible",
            "t": "bad"
          }
        ]
      }
    },
    {
      "id": 39545,
      "symbol": "BILL",
      "name": "Billions Network",
      "price": 0.04597154098476244,
      "market_cap": 111627840.40131845,
      "volume_24h": 163106242.61411688,
      "pct_7d": 15.13326689,
      "pct_30d": -35.83051702,
      "float_ratio": 0.2428194444,
      "score": 0.5319946968658,
      "parts": {
        "float_quality": 0.2428194444,
        "momentum_24h": 0.5462818043333333,
        "momentum_7d": 0.3026653378,
        "momentum_30d": 0,
        "volume_surge": 1
      },
      "dd": {
        "tvl": null,
        "category": null,
        "fees24h": null,
        "liquidity_usd": null,
        "pair_age_days": null,
        "token_age_days": null,
        "flags": []
      }
    },
    {
      "id": 40588,
      "symbol": "ANSEM",
      "name": "The Black Bull",
      "price": 0.22921653185316523,
      "market_cap": 95275991.18539806,
      "volume_24h": 38473948.85638165,
      "pct_7d": -19.61618792,
      "pct_30d": 643827.74746762,
      "float_ratio": 0.4156826622746708,
      "score": 0.5309991923093698,
      "parts": {
        "float_quality": 0.4156826622746708,
        "momentum_24h": 0,
        "momentum_7d": 0,
        "momentum_30d": 1,
        "volume_surge": 0.8076315633707759
      },
      "dd": {
        "tvl": null,
        "category": null,
        "fees24h": null,
        "liquidity_usd": 2118464.86,
        "pair_age_days": 25,
        "token_age_days": null,
        "flags": []
      }
    },
    {
      "id": 25028,
      "symbol": "ORDI",
      "name": "ORDI",
      "price": 3.5293179354939914,
      "market_cap": 74115676.64537382,
      "volume_24h": 11900952.14978757,
      "pct_7d": 7.86249625,
      "pct_30d": 4.52191475,
      "float_ratio": 1,
      "score": 0.5210693300980198,
      "parts": {
        "float_quality": 1,
        "momentum_24h": 0.023618877333333333,
        "momentum_7d": 0.157249925,
        "momentum_30d": 0.045219147499999994,
        "volume_surge": 0.3211453416726084
      },
      "dd": {
        "tvl": null,
        "category": null,
        "fees24h": null,
        "liquidity_usd": null,
        "pair_age_days": null,
        "token_age_days": null,
        "flags": []
      }
    },
    {
      "id": 33788,
      "symbol": "PNUT",
      "name": "Peanut the Squirrel",
      "price": 0.042955192148015575,
      "market_cap": 42948394.31812853,
      "volume_24h": 8088144.72625411,
      "pct_7d": -3.18959889,
      "pct_30d": 0.34616898,
      "float_ratio": 1,
      "score": 0.5208649136853974,
      "parts": {
        "float_quality": 1,
        "momentum_24h": 0,
        "momentum_7d": 0,
        "momentum_30d": 0.0034616898000000003,
        "volume_surge": 0.3766448014956453
      },
      "dd": {
        "tvl": null,
        "category": null,
        "fees24h": null,
        "liquidity_usd": 2624493.16,
        "pair_age_days": 618,
        "token_age_days": null,
        "flags": []
      }
    },
    {
      "id": 10529,
      "symbol": "SUN",
      "name": "Sun [New]",
      "price": 0.018491393189467242,
      "market_cap": 355611810.4553673,
      "volume_24h": 55713580.50197826,
      "pct_7d": 5.19956993,
      "pct_30d": 11.42446053,
      "float_ratio": 1,
      "score": 0.5175508822343253,
      "parts": {
        "float_quality": 1,
        "momentum_24h": 0.016993722,
        "momentum_7d": 0.1039913986,
        "momentum_30d": 0.1142446053,
        "volume_surge": 0.3133393147468079
      },
      "dd": {
        "tvl": 214633814.51430514,
        "category": "Dexs",
        "fees24h": 10630,
        "liquidity_usd": 17244714.06,
        "pair_age_days": 1669,
        "token_age_days": null,
        "flags": [
          {
            "k": "revenu réel",
            "t": "ok"
          }
        ]
      }
    },
    {
      "id": 6892,
      "symbol": "EGLD",
      "name": "MultiversX",
      "price": 3.044678009712041,
      "market_cap": 92341395.46396811,
      "volume_24h": 10998563.40445025,
      "pct_7d": 13.90748512,
      "pct_30d": 4.59125432,
      "float_ratio": 0.9998300424982327,
      "score": 0.5174472975033081,
      "parts": {
        "float_quality": 0.9998300424982327,
        "momentum_24h": 0.22120807266666667,
        "momentum_7d": 0.27814970240000003,
        "momentum_30d": 0.0459125432,
        "volume_surge": 0.23821523054071503
      },
      "dd": {
        "tvl": null,
        "category": null,
        "fees24h": null,
        "liquidity_usd": 189312183.39,
        "pair_age_days": 174,
        "token_age_days": null,
        "flags": []
      }
    },
    {
      "id": 4846,
      "symbol": "KAVA",
      "name": "Kava",
      "price": 0.04437858855464828,
      "market_cap": 48055221.88004252,
      "volume_24h": 8839422.70382654,
      "pct_7d": -1.70487913,
      "pct_30d": -3.08350377,
      "float_ratio": 1,
      "score": 0.5173820637069666,
      "parts": {
        "float_quality": 1,
        "momentum_24h": 0,
        "momentum_7d": 0,
        "momentum_30d": 0,
        "volume_surge": 0.3678860426819745
      },
      "dd": {
        "tvl": null,
        "category": null,
        "fees24h": null,
        "liquidity_usd": null,
        "pair_age_days": null,
        "token_age_days": null,
        "flags": []
      }
    },
    {
      "id": 34880,
      "symbol": "ALCH",
      "name": "Alchemist AI",
      "price": 0.054089742249344014,
      "market_cap": 45976280.911942415,
      "volume_24h": 11889518.5784223,
      "pct_7d": -6.55811505,
      "pct_30d": -9.75717591,
      "float_ratio": 0.85,
      "score": 0.5150304377854932,
      "parts": {
        "float_quality": 0.85,
        "momentum_24h": 0,
        "momentum_7d": 0,
        "momentum_30d": 0,
        "volume_surge": 0.517202276591014
      },
      "dd": {
        "tvl": null,
        "category": null,
        "fees24h": null,
        "liquidity_usd": 2871507.46,
        "pair_age_days": 591,
        "token_age_days": null,
        "flags": []
      }
    },
    {
      "id": 40092,
      "symbol": "O",
      "name": "o1.exchange",
      "price": 0.5539532547397592,
      "market_cap": 88632520.75836147,
      "volume_24h": 150254376.45715392,
      "pct_7d": -5.54336417,
      "pct_30d": 744.71897056,
      "float_ratio": 0.16,
      "score": 0.50412,
      "parts": {
        "float_quality": 0.16,
        "momentum_24h": 0,
        "momentum_7d": 0,
        "momentum_30d": 1,
        "volume_surge": 1
      },
      "dd": {
        "tvl": 767730.0273101894,
        "category": "Staking Rental",
        "fees24h": null,
        "liquidity_usd": 2669468.5,
        "pair_age_days": 27,
        "token_age_days": null,
        "flags": [
          {
            "k": "TVL sans revenu",
            "t": "warn"
          }
        ]
      }
    },
    {
      "id": 21846,
      "symbol": "ID",
      "name": "SPACE ID",
      "price": 0.0377993005339862,
      "market_cap": 74395641.61134648,
      "volume_24h": 10975599.97795448,
      "pct_7d": -2.11461725,
      "pct_30d": 24.42925641,
      "float_ratio": 0.9866321854790163,
      "score": 0.5037976256974868,
      "parts": {
        "float_quality": 0.9866321854790163,
        "momentum_24h": 0,
        "momentum_7d": 0,
        "momentum_30d": 0.2442925641,
        "volume_surge": 0.295060294937507
      },
      "dd": {
        "tvl": null,
        "category": null,
        "fees24h": null,
        "liquidity_usd": 645661.05,
        "pair_age_days": 279,
        "token_age_days": null,
        "flags": []
      }
    },
    {
      "id": 27960,
      "symbol": "NPC",
      "name": "Non-Playable Coin",
      "price": 0.0068857197053462105,
      "market_cap": 52185089.49190413,
      "volume_24h": 5480168.53338551,
      "pct_7d": 20.38744462,
      "pct_30d": 34.11754136,
      "float_ratio": 0.9414437714304915,
      "score": 0.5032849199506786,
      "parts": {
        "float_quality": 0.9414437714304915,
        "momentum_24h": 0,
        "momentum_7d": 0.4077488924,
        "momentum_30d": 0.3411754136,
        "volume_surge": 0.21002813588106195
      },
      "dd": {
        "tvl": null,
        "category": null,
        "fees24h": null,
        "liquidity_usd": 2363988.7,
        "pair_age_days": 1078,
        "token_age_days": null,
        "flags": []
      }
    },
    {
      "id": 4066,
      "symbol": "CHZ",
      "name": "Chiliz",
      "price": 0.01723696677639097,
      "market_cap": 180273716.88673553,
      "volume_24h": 28818355.49608109,
      "pct_7d": -5.58531918,
      "pct_30d": -36.6022899,
      "float_ratio": 1,
      "score": 0.4996561398489495,
      "parts": {
        "float_quality": 1,
        "momentum_24h": 0,
        "momentum_7d": 0,
        "momentum_30d": 0,
        "volume_surge": 0.3197177713286671
      },
      "dd": {
        "tvl": null,
        "category": null,
        "fees24h": null,
        "liquidity_usd": null,
        "pair_age_days": null,
        "token_age_days": null,
        "flags": []
      }
    },
    {
      "id": 2765,
      "symbol": "XYO",
      "name": "XYO",
      "price": 0.0031139264946418114,
      "market_cap": 42978049.74286575,
      "volume_24h": 6834356.83703731,
      "pct_7d": -4.16867358,
      "pct_30d": -12.32990155,
      "float_ratio": 0.9907492663084095,
      "score": 0.4977787670881698,
      "parts": {
        "float_quality": 0.9907492663084095,
        "momentum_24h": 0.030320582666666665,
        "momentum_7d": 0,
        "momentum_30d": 0,
        "volume_surge": 0.31803941211510167
      },
      "dd": {
        "tvl": null,
        "category": null,
        "fees24h": null,
        "liquidity_usd": 333847.85,
        "pair_age_days": 528,
        "token_age_days": null,
        "flags": []
      }
    },
    {
      "id": 2416,
      "symbol": "THETA",
      "name": "Theta Network",
      "price": 0.1484905141321527,
      "market_cap": 148490514.1321527,
      "volume_24h": 20020146.61559924,
      "pct_7d": 6.47929321,
      "pct_30d": -5.72849164,
      "float_ratio": 1,
      "score": 0.49627371846212,
      "parts": {
        "float_quality": 1,
        "momentum_24h": 0.027791507,
        "momentum_7d": 0.12958586419999998,
        "momentum_30d": 0,
        "volume_surge": 0.2696488288508696
      },
      "dd": {
        "tvl": null,
        "category": null,
        "fees24h": null,
        "liquidity_usd": 1001904659.59,
        "pair_age_days": 426,
        "token_age_days": null,
        "flags": []
      }
    },
    {
      "id": 29814,
      "symbol": "ETHFI",
      "name": "ether.fi",
      "price": 0.4375291246145699,
      "market_cap": 405749764.9985235,
      "volume_24h": 49923139.79852411,
      "pct_7d": 2.36440689,
      "pct_30d": 41.31932303,
      "float_ratio": 0.927366299,
      "score": 0.49478355174414607,
      "parts": {
        "float_quality": 0.927366299,
        "momentum_24h": 0.190059255,
        "momentum_7d": 0.047288137800000005,
        "momentum_30d": 0.4131932303,
        "volume_surge": 0.24607846562132096
      },
      "dd": {
        "tvl": 2983656318.8588095,
        "category": "Liquid Restaking",
        "fees24h": null,
        "liquidity_usd": 696431.27,
        "pair_age_days": 341,
        "token_age_days": null,
        "flags": [
          {
            "k": "TVL sans revenu",
            "t": "warn"
          }
        ]
      }
    },
    {
      "id": 27750,
      "symbol": "TOSHI",
      "name": "Toshi",
      "price": 0.00011332918076980723,
      "market_cap": 47674113.63761846,
      "volume_24h": 7223833.94525559,
      "pct_7d": -4.8786158,
      "pct_30d": -11.21561744,
      "float_ratio": 0.99995093132392,
      "score": 0.4935038699903427,
      "parts": {
        "float_quality": 0.99995093132392,
        "momentum_24h": 0,
        "momentum_7d": 0,
        "momentum_30d": 0,
        "volume_surge": 0.3030505821320794
      },
      "dd": {
        "tvl": null,
        "category": null,
        "fees24h": null,
        "liquidity_usd": 376972.08,
        "pair_age_days": 343,
        "token_age_days": null,
        "flags": []
      }
    },
    {
      "id": 7226,
      "symbol": "INJ",
      "name": "Injective",
      "price": 4.852501008980515,
      "market_cap": 485109157.57999516,
      "volume_24h": 65595881.77073423,
      "pct_7d": 4.08316277,
      "pct_30d": -9.0783408,
      "float_ratio": 0.999709545,
      "score": 0.48957641401273444,
      "parts": {
        "float_quality": 0.999709545,
        "momentum_24h": 0,
        "momentum_7d": 0.08166325540000001,
        "momentum_30d": 0,
        "volume_surge": 0.27043761489873497
      },
      "dd": {
        "tvl": 10501407.818096623,
        "category": "Bridge",
        "fees24h": null,
        "liquidity_usd": 363757.95,
        "pair_age_days": 4,
        "token_age_days": null,
        "flags": [
          {
            "k": "TVL sans revenu",
            "t": "warn"
          },
          {
            "k": "paire récente",
            "t": "warn"
          }
        ]
      }
    },
    {
      "id": 33223,
      "symbol": "LAB",
      "name": "LAB",
      "price": 0.4788219985927379,
      "market_cap": 149438040.71169227,
      "volume_24h": 127990472.0118623,
      "pct_7d": -97.04063708,
      "pct_30d": -95.15374039,
      "float_ratio": 0.31524766262626264,
      "score": 0.4884246071232323,
      "parts": {
        "float_quality": 0.31524766262626264,
        "momentum_24h": 0,
        "momentum_7d": 0,
        "momentum_30d": 0,
        "volume_surge": 1
      },
      "dd": {
        "tvl": 2401060.4896097896,
        "category": "Lending",
        "fees24h": null,
        "liquidity_usd": 279481.21,
        "pair_age_days": null,
        "token_age_days": null,
        "flags": [
          {
            "k": "TVL sans revenu",
            "t": "warn"
          }
        ]
      }
    },
    {
      "id": 33881,
      "symbol": "BAN",
      "name": "Comedian",
      "price": 0.07179035686801309,
      "market_cap": 71787618.71201178,
      "volume_24h": 9705892.45005358,
      "pct_7d": -3.16536018,
      "pct_30d": -0.47418609,
      "float_ratio": 1,
      "score": 0.4815093161105809,
      "parts": {
        "float_quality": 1,
        "momentum_24h": 0,
        "momentum_7d": 0,
        "momentum_30d": 0,
        "volume_surge": 0.27040575030049163
      },
      "dd": {
        "tvl": 0,
        "category": "Yield",
        "fees24h": null,
        "liquidity_usd": 2527501.41,
        "pair_age_days": 624,
        "token_age_days": null,
        "flags": []
      }
    },
    {
      "id": 33824,
      "symbol": "SYRUP",
      "name": "Maple Finance",
      "price": 0.18752035281038026,
      "market_cap": 223338485.42115864,
      "volume_24h": 15273967.7650608,
      "pct_7d": 15.920921,
      "pct_30d": 41.62804612,
      "float_ratio": 0.9568818541486134,
      "score": 0.47892628642897633,
      "parts": {
        "float_quality": 0.9568818541486134,
        "momentum_24h": 0,
        "momentum_7d": 0.31841842,
        "momentum_30d": 0.4162804612,
        "volume_surge": 0.13677864552773378
      },
      "dd": {
        "tvl": 2287024006.0412893,
        "category": "Lending",
        "fees24h": 0,
        "liquidity_usd": 1935578.93,
        "pair_age_days": 455,
        "token_age_days": null,
        "flags": [
          {
            "k": "TVL sans revenu",
            "t": "warn"
          }
        ]
      }
    },
    {
      "id": 35347,
      "symbol": "MELANIA",
      "name": "Official Melania Meme",
      "price": 0.08165010940844267,
      "market_cap": 81649777.34803788,
      "volume_24h": 10631497.53581352,
      "pct_7d": -0.78559992,
      "pct_30d": -5.86512104,
      "float_ratio": 0.9999999999999959,
      "score": 0.477833478553223,
      "parts": {
        "float_quality": 0.9999999999999959,
        "momentum_24h": 0,
        "momentum_7d": 0,
        "momentum_30d": 0,
        "volume_surge": 0.26041706128593634
      },
      "dd": {
        "tvl": 0,
        "category": "Meme",
        "fees24h": null,
        "liquidity_usd": 10451646.78,
        "pair_age_days": 538,
        "token_age_days": null,
        "flags": []
      }
    },
    {
      "id": 40212,
      "symbol": "MUB",
      "name": "Micron Technology Tokenized bStocks",
      "price": 979.6440008439781,
      "market_cap": 93430044.32154271,
      "volume_24h": 12038589.07057994,
      "pct_7d": -6.0856883,
      "pct_30d": 1.09684701,
      "float_ratio": 1,
      "score": 0.4776572424792782,
      "parts": {
        "float_quality": 1,
        "momentum_24h": 0,
        "momentum_7d": 0,
        "momentum_30d": 0.0109684701,
        "volume_surge": 0.2577027370157018
      },
      "dd": {
        "tvl": null,
        "category": null,
        "fees24h": null,
        "liquidity_usd": 13908.71,
        "pair_age_days": 18,
        "token_age_days": null,
        "flags": [
          {
            "k": "liquidité faible",
            "t": "bad"
          }
        ]
      }
    }
  ]
}