{
  "updated_at": "2026-05-23T00:00:00.000Z",
  "source": "SAMPLE",
  "note": "Données EXEMPLE — remplacées au premier run du scan (GitHub Actions).",
  "weights": { "float_quality": 0.25, "momentum_7d": 0.25, "momentum_30d": 0.2, "volume_surge": 0.3 },
  "count": 3,
  "candidates": [
    { "id": 28412, "symbol": "IO", "name": "io.net", "price": 0.152, "market_cap": 50800000, "volume_24h": 39000000, "pct_7d": 11.9, "pct_30d": 22.0, "float_ratio": 0.42, "score": 0.50, "parts": {} },
    { "id": 7431, "symbol": "AKT", "name": "Akash Network", "price": 0.85, "market_cap": 250000000, "volume_24h": 13300000, "pct_7d": -8.3, "pct_30d": 46.6, "float_ratio": 0.76, "score": 0.31, "parts": {} },
    { "id": 5665, "symbol": "HNT", "name": "Helium", "price": 0.80, "market_cap": 150000000, "volume_24h": 3000000, "pct_7d": -10.5, "pct_30d": -5.0, "float_ratio": 0.84, "score": 0.22, "parts": {} }
  ]
}
