{
  "updated_at": "2026-06-22T06:21:00.405Z",
  "source": "coinmarketcap",
  "note": "Triage, pas un prédicteur. Le tracker dit si le score vaut quelque chose.",
  "weights_mode": "appris",
  "weights": {
    "float_quality": 0.6,
    "momentum_24h": 0.075,
    "momentum_7d": 0.1,
    "momentum_30d": 0.075,
    "volume_surge": 0.15
  },
  "dd_status": {
    "coingecko": true,
    "cg": 0,
    "dd": 34
  },
  "count": 50,
  "candidates": [
    {
      "id": 12147,
      "symbol": "SYN",
      "name": "Synapse",
      "price": 0.21259567145855257,
      "market_cap": 47170102.07182612,
      "volume_24h": 77916281.58711547,
      "pct_7d": 467.56678984,
      "pct_30d": 350.32643038,
      "float_ratio": 0.9413204683521113,
      "score": 0.9647922810112668,
      "parts": {
        "float_quality": 0.9413204683521113,
        "momentum_24h": 1,
        "momentum_7d": 1,
        "momentum_30d": 1,
        "volume_surge": 1
      },
      "dd": {
        "tvl": 11370758.646407627,
        "category": "Cross Chain Bridge",
        "fees24h": 9,
        "liquidity_usd": 126566.11,
        "pair_age_days": 1758,
        "token_age_days": null,
        "flags": [
          {
            "k": "TVL sans revenu",
            "t": "warn"
          }
        ]
      }
    },
    {
      "id": 9543,
      "symbol": "BICO",
      "name": "Biconomy",
      "price": 0.04085108415796679,
      "market_cap": 40861003.256162345,
      "volume_24h": 107026918.11515808,
      "pct_7d": 113.3189539,
      "pct_30d": 57.73772642,
      "float_ratio": 1.0002428111370851,
      "score": 0.893303294815,
      "parts": {
        "float_quality": 1,
        "momentum_24h": 0,
        "momentum_7d": 1,
        "momentum_30d": 0.5773772642,
        "volume_surge": 1
      },
      "dd": {
        "tvl": 100361.00731605997,
        "category": "Bridge",
        "fees24h": null,
        "liquidity_usd": null,
        "pair_age_days": null,
        "token_age_days": null,
        "flags": [
          {
            "k": "TVL sans revenu",
            "t": "warn"
          }
        ]
      }
    },
    {
      "id": 34083,
      "symbol": "ZEREBRO",
      "name": "Zerebro",
      "price": 0.03999633803400857,
      "market_cap": 39994272.33903194,
      "volume_24h": 13386383.18580875,
      "pct_7d": 56.12985768,
      "pct_30d": 78.18561689,
      "float_ratio": 0.9999997700973631,
      "score": 0.859051326802907,
      "parts": {
        "float_quality": 0.9999997700973631,
        "momentum_24h": 0,
        "momentum_7d": 1,
        "momentum_30d": 0.7818561689000001,
        "volume_surge": 0.6694150138465935
      },
      "dd": {
        "tvl": null,
        "category": "Solana Ecosystem",
        "fees24h": null,
        "liquidity_usd": 2769385.88,
        "pair_age_days": 601,
        "token_age_days": null,
        "flags": []
      }
    },
    {
      "id": 39459,
      "symbol": "WOJAK",
      "name": "wojak (wojakcto.com)",
      "price": 1.3335622761393326e-7,
      "market_cap": 40795473.81160158,
      "volume_24h": 2594102.93675931,
      "pct_7d": 110.51864319,
      "pct_30d": 116.1566308,
      "float_ratio": 1,
      "score": 0.8240082351343073,
      "parts": {
        "float_quality": 1,
        "momentum_24h": 0.399091101,
        "momentum_7d": 1,
        "momentum_30d": 1,
        "volume_surge": 0.1271760170620491
      },
      "dd": {
        "tvl": null,
        "category": "Meme",
        "fees24h": null,
        "liquidity_usd": 1178130.8,
        "pair_age_days": 146,
        "token_age_days": null,
        "flags": []
      }
    },
    {
      "id": 35766,
      "symbol": "SIREN",
      "name": "siren",
      "price": 0.07116286117196884,
      "market_cap": 51550584.921419516,
      "volume_24h": 10804517.88253381,
      "pct_7d": 29.40752544,
      "pct_30d": -86.02595509,
      "float_ratio": 1,
      "score": 0.7966922300565518,
      "parts": {
        "float_quality": 1,
        "momentum_24h": 1,
        "momentum_7d": 0.5881505088,
        "momentum_30d": 0,
        "volume_surge": 0.41918119451034513
      },
      "dd": {
        "tvl": null,
        "category": "BNB Chain Ecosystem",
        "fees24h": null,
        "liquidity_usd": 2291091.97,
        "pair_age_days": 498,
        "token_age_days": null,
        "flags": []
      }
    },
    {
      "id": 37006,
      "symbol": "SPYX",
      "name": "SP500 tokenized ETF (xStock)",
      "price": 749.4730259280783,
      "market_cap": 162342877.9803595,
      "volume_24h": 135880998.97525525,
      "pct_7d": -0.61157813,
      "pct_30d": 0.2973274,
      "float_ratio": 1,
      "score": 0.7502229955500002,
      "parts": {
        "float_quality": 1,
        "momentum_24h": 0,
        "momentum_7d": 0,
        "momentum_30d": 0.002973274,
        "volume_surge": 1
      },
      "dd": {
        "tvl": null,
        "category": "Tokenized Assets",
        "fees24h": null,
        "liquidity_usd": null,
        "pair_age_days": null,
        "token_age_days": null,
        "flags": []
      }
    },
    {
      "id": 21846,
      "symbol": "ID",
      "name": "SPACE ID",
      "price": 0.03747835018482446,
      "market_cap": 54629696.18748794,
      "volume_24h": 135605206.26296687,
      "pct_7d": 34.11252719,
      "pct_30d": 19.57061233,
      "float_ratio": 0.7307012814933396,
      "score": 0.746323782523504,
      "parts": {
        "float_quality": 0.7307012814933396,
        "momentum_24h": 1,
        "momentum_7d": 0.6822505438,
        "momentum_30d": 0.1957061233,
        "volume_surge": 1
      },
      "dd": {
        "tvl": null,
        "category": "Smart Contract Platform",
        "fees24h": null,
        "liquidity_usd": null,
        "pair_age_days": null,
        "token_age_days": null,
        "flags": []
      }
    },
    {
      "id": 28782,
      "symbol": "POPCAT",
      "name": "Popcat (SOL)",
      "price": 0.04803471329820508,
      "market_cap": 47070968.83622937,
      "volume_24h": 17296700.20478397,
      "pct_7d": 12.20791381,
      "pct_30d": -10.31997833,
      "float_ratio": 1,
      "score": 0.7421634140176391,
      "parts": {
        "float_quality": 1,
        "momentum_24h": 0.100127649,
        "momentum_7d": 0.24415827620000002,
        "momentum_30d": 0,
        "volume_surge": 0.7349200848175924
      },
      "dd": {
        "tvl": null,
        "category": "Solana Ecosystem",
        "fees24h": null,
        "liquidity_usd": 3002050.3,
        "pair_age_days": 922,
        "token_age_days": null,
        "flags": []
      }
    },
    {
      "id": 36992,
      "symbol": "NVDAX",
      "name": "NVIDIA tokenized stock (xStock)",
      "price": 209.2858400064322,
      "market_cap": 136897450.05788764,
      "volume_24h": 57875314.34127712,
      "pct_7d": -0.2791198,
      "pct_30d": -2.08840501,
      "float_ratio": 1,
      "score": 0.7269086922264468,
      "parts": {
        "float_quality": 1,
        "momentum_24h": 0.001059874,
        "momentum_7d": 0,
        "momentum_30d": 0,
        "volume_surge": 0.845528011176312
      },
      "dd": {
        "tvl": null,
        "category": "Tokenized Assets",
        "fees24h": null,
        "liquidity_usd": null,
        "pair_age_days": null,
        "token_age_days": null,
        "flags": []
      }
    },
    {
      "id": 3701,
      "symbol": "RIF",
      "name": "Rootstock Infrastructure Framework",
      "price": 0.09126824374005876,
      "market_cap": 91268243.74005876,
      "volume_24h": 8583363.25747969,
      "pct_7d": -12.85573677,
      "pct_30d": 96.25230007,
      "float_ratio": 1,
      "score": 0.7183042150488272,
      "parts": {
        "float_quality": 1,
        "momentum_24h": 0.23868472433333335,
        "momentum_7d": 0,
        "momentum_30d": 0.9625230007000001,
        "volume_surge": 0.18809090447551463
      },
      "dd": {
        "tvl": null,
        "category": "Solana Ecosystem",
        "fees24h": null,
        "liquidity_usd": null,
        "pair_age_days": null,
        "token_age_days": null,
        "flags": []
      }
    },
    {
      "id": 40217,
      "symbol": "SPCXB",
      "name": "SpaceX Tokenized bStocks",
      "price": 179.22035795215356,
      "market_cap": 40212231.833838925,
      "volume_24h": 13035989.70579785,
      "pct_7d": 5.54455968,
      "pct_30d": 12.01272372,
      "float_ratio": 1,
      "score": 0.7173525755338473,
      "parts": {
        "float_quality": 1,
        "momentum_24h": 0,
        "momentum_7d": 0.1108911936,
        "momentum_30d": 0.1201272372,
        "volume_surge": 0.6483594225589815
      },
      "dd": {
        "tvl": null,
        "category": "Tokenized Assets",
        "fees24h": null,
        "liquidity_usd": 330662.4,
        "pair_age_days": 9,
        "token_age_days": null,
        "flags": [
          {
            "k": "paire récente",
            "t": "warn"
          }
        ]
      }
    },
    {
      "id": 29743,
      "symbol": "BRETT",
      "name": "Brett (Based)",
      "price": 0.005588683751255869,
      "market_cap": 55886823.790792815,
      "volume_24h": 19238077.96011977,
      "pct_7d": -14.79004959,
      "pct_30d": -22.43934971,
      "float_ratio": 1,
      "score": 0.7032698406629929,
      "parts": {
        "float_quality": 1,
        "momentum_24h": 0,
        "momentum_7d": 0,
        "momentum_30d": 0,
        "volume_surge": 0.6884656044199522
      },
      "dd": {
        "tvl": null,
        "category": "BNB Chain Ecosystem",
        "fees24h": null,
        "liquidity_usd": null,
        "pair_age_days": null,
        "token_age_days": null,
        "flags": []
      }
    },
    {
      "id": 8536,
      "symbol": "MASK",
      "name": "Mask Network",
      "price": 0.3988018909638119,
      "market_cap": 39880189.09638119,
      "volume_24h": 11286373.95858824,
      "pct_7d": 5.93317906,
      "pct_30d": -12.27666708,
      "float_ratio": 1,
      "score": 0.6967684677713236,
      "parts": {
        "float_quality": 1,
        "momentum_24h": 0,
        "momentum_7d": 0.11866358119999999,
        "momentum_30d": 0,
        "volume_surge": 0.5660140643421568
      },
      "dd": {
        "tvl": null,
        "category": null,
        "fees24h": null,
        "liquidity_usd": null,
        "pair_age_days": null,
        "token_age_days": null,
        "flags": []
      }
    },
    {
      "id": 33788,
      "symbol": "PNUT",
      "name": "Peanut the Squirrel",
      "price": 0.044776913865108375,
      "market_cap": 44769837.02323582,
      "volume_24h": 12154832.96912057,
      "pct_7d": -0.57014845,
      "pct_30d": -18.03983219,
      "float_ratio": 1,
      "score": 0.683144366338842,
      "parts": {
        "float_quality": 1,
        "momentum_24h": 0.022607435333333332,
        "momentum_7d": 0,
        "momentum_30d": 0,
        "volume_surge": 0.5429920579256134
      },
      "dd": {
        "tvl": null,
        "category": null,
        "fees24h": null,
        "liquidity_usd": 2617965.2,
        "pair_age_days": 598,
        "token_age_days": null,
        "flags": []
      }
    },
    {
      "id": 38014,
      "symbol": "MUon",
      "name": "Micron Technology Tokenized Stock (Ondo)",
      "price": 1160.3645901938119,
      "market_cap": 85576236.71086422,
      "volume_24h": 3077348.92033067,
      "pct_7d": 12.72294963,
      "pct_30d": 56.69203902,
      "float_ratio": 1,
      "score": 0.6823480377237031,
      "parts": {
        "float_quality": 1,
        "momentum_24h": 0.047933506333333334,
        "momentum_7d": 0.2544589926,
        "momentum_30d": 0.5669203902000001,
        "volume_surge": 0.07192064149135433
      },
      "dd": {
        "tvl": null,
        "category": null,
        "fees24h": null,
        "liquidity_usd": null,
        "pair_age_days": null,
        "token_age_days": null,
        "flags": []
      }
    },
    {
      "id": 26081,
      "symbol": "FDUSD",
      "name": "First Digital USD",
      "price": 0.9984425347455793,
      "market_cap": 351967499.78401476,
      "volume_24h": 92020401.6721899,
      "pct_7d": 0.08235575,
      "pct_30d": 0.12758631,
      "float_ratio": 1,
      "score": 0.6787020703782772,
      "parts": {
        "float_quality": 1,
        "momentum_24h": 0.00010598199999999999,
        "momentum_7d": 0.0016471150000000002,
        "momentum_30d": 0.0012758631000000002,
        "volume_surge": 0.5228914699718487
      },
      "dd": {
        "tvl": null,
        "category": null,
        "fees24h": null,
        "liquidity_usd": null,
        "pair_age_days": null,
        "token_age_days": null,
        "flags": []
      }
    },
    {
      "id": 23121,
      "symbol": "BLUR",
      "name": "Blur",
      "price": 0.01568569391085733,
      "market_cap": 44335634.00348123,
      "volume_24h": 16496274.96796504,
      "pct_7d": -15.87947994,
      "pct_30d": -29.08724036,
      "float_ratio": 0.9421670951769406,
      "score": 0.6786318516987978,
      "parts": {
        "float_quality": 0.9421670951769406,
        "momentum_24h": 0.022779452,
        "momentum_7d": 0,
        "momentum_30d": 0,
        "volume_surge": 0.7441542379508886
      },
      "dd": {
        "tvl": 13549224.742547285,
        "category": "NFT Marketplace",
        "fees24h": 0,
        "liquidity_usd": null,
        "pair_age_days": null,
        "token_age_days": null,
        "flags": [
          {
            "k": "TVL sans revenu",
            "t": "warn"
          }
        ]
      }
    },
    {
      "id": 4006,
      "symbol": "AWE",
      "name": "AWE",
      "price": 0.05723249896330036,
      "market_cap": 111169566.8346402,
      "volume_24h": 14329603.54567865,
      "pct_7d": 5.28192319,
      "pct_30d": 17.59372101,
      "float_ratio": 1.0000000000139349,
      "score": 0.67592500590847,
      "parts": {
        "float_quality": 1,
        "momentum_24h": 0.17995044433333335,
        "momentum_7d": 0.1056384638,
        "momentum_30d": 0.1759372101,
        "volume_surge": 0.25779723630646684
      },
      "dd": {
        "tvl": null,
        "category": null,
        "fees24h": null,
        "liquidity_usd": 374612.56,
        "pair_age_days": 396,
        "token_age_days": null,
        "flags": []
      }
    },
    {
      "id": 28752,
      "symbol": "WIF",
      "name": "dogwifhat",
      "price": 0.1635909310654191,
      "market_cap": 163401002.32980734,
      "volume_24h": 39442227.93751415,
      "pct_7d": -2.0223256,
      "pct_30d": -13.61555603,
      "float_ratio": 1,
      "score": 0.6757922202622676,
      "parts": {
        "float_quality": 1,
        "momentum_24h": 0.045030844,
        "momentum_7d": 0,
        "momentum_30d": 0,
        "volume_surge": 0.4827660464151163
      },
      "dd": {
        "tvl": null,
        "category": null,
        "fees24h": null,
        "liquidity_usd": 4262173.26,
        "pair_age_days": 944,
        "token_age_days": null,
        "flags": []
      }
    },
    {
      "id": 4846,
      "symbol": "KAVA",
      "name": "Kava",
      "price": 0.04776055411472688,
      "market_cap": 51717373.219075195,
      "volume_24h": 11859292.80825735,
      "pct_7d": 2.96454586,
      "pct_30d": -20.4038586,
      "float_ratio": 1,
      "score": 0.6749862584475795,
      "parts": {
        "float_quality": 1,
        "momentum_24h": 0.0035236186666666664,
        "momentum_7d": 0.059290917199999994,
        "momentum_30d": 0,
        "volume_surge": 0.4586193021838636
      },
      "dd": {
        "tvl": null,
        "category": null,
        "fees24h": null,
        "liquidity_usd": null,
        "pair_age_days": null,
        "token_age_days": null,
        "flags": []
      }
    },
    {
      "id": 33093,
      "symbol": "MOODENG",
      "name": "Moo Deng (moodengsol.com)",
      "price": 0.04036284498416841,
      "market_cap": 39958077.94569425,
      "volume_24h": 9824537.52217469,
      "pct_7d": -3.03801659,
      "pct_30d": -18.76715134,
      "float_ratio": 1,
      "score": 0.6737613370857847,
      "parts": {
        "float_quality": 1,
        "momentum_24h": 0,
        "momentum_7d": 0,
        "momentum_30d": 0,
        "volume_surge": 0.49174224723856363
      },
      "dd": {
        "tvl": null,
        "category": null,
        "fees24h": null,
        "liquidity_usd": 2192688.07,
        "pair_age_days": 649,
        "token_age_days": null,
        "flags": []
      }
    },
    {
      "id": 36300,
      "symbol": "SKYAI",
      "name": "SKYAI",
      "price": 0.3923564497992035,
      "market_cap": 392356449.7992035,
      "volume_24h": 20318896.79643972,
      "pct_7d": 3.19207754,
      "pct_30d": 29.08794036,
      "float_ratio": 1,
      "score": 0.6724594885989208,
      "parts": {
        "float_quality": 1,
        "momentum_24h": 0.382977723,
        "momentum_7d": 0.06384155080000001,
        "momentum_30d": 0.29087940360000003,
        "volume_surge": 0.10357366015947148
      },
      "dd": {
        "tvl": null,
        "category": null,
        "fees24h": null,
        "liquidity_usd": 14325103.08,
        "pair_age_days": 428,
        "token_age_days": null,
        "flags": []
      }
    },
    {
      "id": 25028,
      "symbol": "ORDI",
      "name": "ORDI",
      "price": 3.2640745547090035,
      "market_cap": 68545565.64888908,
      "volume_24h": 16088148.0932196,
      "pct_7d": -6.56451695,
      "pct_30d": -17.59855465,
      "float_ratio": 1,
      "score": 0.6704122051116826,
      "parts": {
        "float_quality": 1,
        "momentum_24h": 0,
        "momentum_7d": 0,
        "momentum_30d": 0,
        "volume_surge": 0.4694147007445504
      },
      "dd": {
        "tvl": null,
        "category": null,
        "fees24h": null,
        "liquidity_usd": null,
        "pair_age_days": null,
        "token_age_days": null,
        "flags": []
      }
    },
    {
      "id": 33881,
      "symbol": "BAN",
      "name": "Comedian",
      "price": 0.07251808664079099,
      "market_cap": 72515320.72844842,
      "volume_24h": 10134708.13841347,
      "pct_7d": -3.20875609,
      "pct_30d": -13.35308733,
      "float_ratio": 1,
      "score": 0.6661047865438797,
      "parts": {
        "float_quality": 1,
        "momentum_24h": 0.322358979,
        "momentum_7d": 0,
        "momentum_30d": 0,
        "volume_surge": 0.2795190874591976
      },
      "dd": {
        "tvl": 0,
        "category": "Yield",
        "fees24h": null,
        "liquidity_usd": 2483249.45,
        "pair_age_days": 604,
        "token_age_days": null,
        "flags": []
      }
    },
    {
      "id": 5665,
      "symbol": "HNT",
      "name": "Helium",
      "price": 0.2925333989364701,
      "market_cap": 54505243.639445685,
      "volume_24h": 8065740.15305572,
      "pct_7d": -1.97804608,
      "pct_30d": -62.69442244,
      "float_ratio": 1,
      "score": 0.6608674328160167,
      "parts": {
        "float_quality": 1,
        "momentum_24h": 0.21964179333333333,
        "momentum_7d": 0,
        "momentum_30d": 0,
        "volume_surge": 0.29596198877344376
      },
      "dd": {
        "tvl": 0,
        "category": "Chain",
        "fees24h": null,
        "liquidity_usd": 547786416.14,
        "pair_age_days": 256,
        "token_age_days": null,
        "flags": []
      }
    },
    {
      "id": 37041,
      "symbol": "HOODX",
      "name": "Robinhood tokenized stock (xStock)",
      "price": 107.54247784121502,
      "market_cap": 158055727.39633778,
      "volume_24h": 1726512.87824435,
      "pct_7d": 10.93604486,
      "pct_30d": 47.24216944,
      "float_ratio": 1,
      "score": 0.6605807499832045,
      "parts": {
        "float_quality": 1,
        "momentum_24h": 0,
        "momentum_7d": 0.21872089720000001,
        "momentum_30d": 0.4724216944,
        "volume_surge": 0.02184688788802922
      },
      "dd": {
        "tvl": null,
        "category": null,
        "fees24h": null,
        "liquidity_usd": null,
        "pair_age_days": null,
        "token_age_days": null,
        "flags": []
      }
    },
    {
      "id": 27659,
      "symbol": "MOG",
      "name": "Mog Coin",
      "price": 1.1255472634107864e-7,
      "market_cap": 43960221.0554027,
      "volume_24h": 8493709.91475365,
      "pct_7d": -2.05517644,
      "pct_30d": -17.71902202,
      "float_ratio": 1,
      "score": 0.6579640619007519,
      "parts": {
        "float_quality": 1,
        "momentum_24h": 0,
        "momentum_7d": 0,
        "momentum_30d": 0,
        "volume_surge": 0.3864270793383453
      },
      "dd": {
        "tvl": null,
        "category": null,
        "fees24h": null,
        "liquidity_usd": 4570532.06,
        "pair_age_days": 1068,
        "token_age_days": null,
        "flags": []
      }
    },
    {
      "id": 10529,
      "symbol": "SUN",
      "name": "Sun [New]",
      "price": 0.017323428093087543,
      "market_cap": 333150431.89851296,
      "volume_24h": 58822372.26523776,
      "pct_7d": 1.83683958,
      "pct_30d": -13.82155695,
      "float_ratio": 1,
      "score": 0.6577873341514652,
      "parts": {
        "float_quality": 1,
        "momentum_24h": 0.015259407000000001,
        "momentum_7d": 0.0367367916,
        "momentum_30d": 0,
        "volume_surge": 0.35312799644310067
      },
      "dd": {
        "tvl": 213218653.81092867,
        "category": "Dexs",
        "fees24h": 9096,
        "liquidity_usd": 16555216.21,
        "pair_age_days": 1649,
        "token_age_days": null,
        "flags": [
          {
            "k": "revenu réel",
            "t": "ok"
          }
        ]
      }
    },
    {
      "id": 18876,
      "symbol": "APE",
      "name": "ApeCoin",
      "price": 0.139742092445532,
      "market_cap": 139742092.445532,
      "volume_24h": 15794655.22142564,
      "pct_7d": 5.8453087,
      "pct_30d": 2.13163299,
      "float_ratio": 1,
      "score": 0.655712898198402,
      "parts": {
        "float_quality": 1,
        "momentum_24h": 0.11353867733333334,
        "momentum_7d": 0.116906174,
        "momentum_30d": 0.0213163299,
        "volume_surge": 0.2260543683726792
      },
      "dd": {
        "tvl": 0,
        "category": "Yield",
        "fees24h": null,
        "liquidity_usd": null,
        "pair_age_days": null,
        "token_age_days": null,
        "flags": []
      }
    },
    {
      "id": 4944,
      "symbol": "TRB",
      "name": "Tellor",
      "price": 13.75654342719362,
      "market_cap": 38360052.564012274,
      "volume_24h": 9032266.9172631,
      "pct_7d": -0.65478226,
      "pct_30d": -20.62674603,
      "float_ratio": 0.9723782702968854,
      "score": 0.6551814212988444,
      "parts": {
        "float_quality": 0.9723782702968854,
        "momentum_24h": 0.014885189333333333,
        "momentum_7d": 0,
        "momentum_30d": 0,
        "volume_surge": 0.4709204661380875
      },
      "dd": {
        "tvl": null,
        "category": null,
        "fees24h": null,
        "liquidity_usd": null,
        "pair_age_days": null,
        "token_age_days": null,
        "flags": []
      }
    },
    {
      "id": 39880,
      "symbol": "ASTEROID",
      "name": "Asteroid Shiba",
      "price": 0.00012921556770124058,
      "market_cap": 54359697.1762349,
      "volume_24h": 4335701.82867601,
      "pct_7d": 15.2547035,
      "pct_30d": -55.16101632,
      "float_ratio": 1,
      "score": 0.6544372545813779,
      "parts": {
        "float_quality": 1,
        "momentum_24h": 0,
        "momentum_7d": 0.30509407,
        "momentum_30d": 0,
        "volume_surge": 0.15951898387585212
      },
      "dd": {
        "tvl": null,
        "category": null,
        "fees24h": null,
        "liquidity_usd": 2316447.11,
        "pair_age_days": 649,
        "token_age_days": null,
        "flags": []
      }
    },
    {
      "id": 27750,
      "symbol": "TOSHI",
      "name": "Toshi",
      "price": 0.00012368385600443864,
      "market_cap": 52030010.289901964,
      "volume_24h": 9098974.24512408,
      "pct_7d": -9.15309275,
      "pct_30d": -23.81274097,
      "float_ratio": 0.9999509712276785,
      "score": 0.6524343869589755,
      "parts": {
        "float_quality": 0.9999509712276785,
        "momentum_24h": 0,
        "momentum_7d": 0,
        "momentum_30d": 0,
        "volume_surge": 0.34975869481578853
      },
      "dd": {
        "tvl": null,
        "category": null,
        "fees24h": null,
        "liquidity_usd": 402766.33,
        "pair_age_days": 323,
        "token_age_days": null,
        "flags": []
      }
    },
    {
      "id": 32644,
      "symbol": "EURI",
      "name": "Eurite",
      "price": 1.144885257919649,
      "market_cap": 56807521.226760074,
      "volume_24h": 9585344.84347116,
      "pct_7d": -1.33154494,
      "pct_30d": -1.2707189,
      "float_ratio": 1,
      "score": 0.6506201184445759,
      "parts": {
        "float_quality": 1,
        "momentum_24h": 0,
        "momentum_7d": 0,
        "momentum_30d": 0,
        "volume_surge": 0.3374674562971719
      },
      "dd": {
        "tvl": null,
        "category": null,
        "fees24h": null,
        "liquidity_usd": null,
        "pair_age_days": null,
        "token_age_days": null,
        "flags": []
      }
    },
    {
      "id": 7226,
      "symbol": "INJ",
      "name": "Injective",
      "price": 4.898012911209478,
      "market_cap": 489659025.8869353,
      "volume_24h": 76664569.83449847,
      "pct_7d": -6.36261494,
      "pct_30d": 1.3769066,
      "float_ratio": 0.999709545,
      "score": 0.6478285836126073,
      "parts": {
        "float_quality": 0.999709545,
        "momentum_24h": 0,
        "momentum_7d": 0,
        "momentum_30d": 0.013769066000000002,
        "volume_surge": 0.3131345110840485
      },
      "dd": {
        "tvl": 12013837.848197429,
        "category": "Bridge",
        "fees24h": null,
        "liquidity_usd": null,
        "pair_age_days": null,
        "token_age_days": null,
        "flags": [
          {
            "k": "TVL sans revenu",
            "t": "warn"
          }
        ]
      }
    },
    {
      "id": 24911,
      "symbol": "TURBO",
      "name": "Turbo",
      "price": 0.000877804869415496,
      "market_cap": 60568535.980891176,
      "volume_24h": 9196101.2294254,
      "pct_7d": -5.49697406,
      "pct_30d": -21.63282643,
      "float_ratio": 1,
      "score": 0.6460093642765885,
      "parts": {
        "float_quality": 1,
        "momentum_24h": 0.006139484,
        "momentum_7d": 0,
        "momentum_30d": 0,
        "volume_surge": 0.3036593531772565
      },
      "dd": {
        "tvl": null,
        "category": null,
        "fees24h": null,
        "liquidity_usd": 118426.67,
        "pair_age_days": 1147,
        "token_age_days": null,
        "flags": []
      }
    },
    {
      "id": 34926,
      "symbol": "ARC",
      "name": "AI Rig Complex",
      "price": 0.0807462016674958,
      "market_cap": 80746065.9331308,
      "volume_24h": 4026448.70471736,
      "pct_7d": 3.75220809,
      "pct_30d": 26.32427402,
      "float_ratio": 1,
      "score": 0.6459225204728669,
      "parts": {
        "float_quality": 1,
        "momentum_24h": 0.04953636533333334,
        "momentum_7d": 0.0750441618,
        "momentum_30d": 0.2632427402,
        "volume_surge": 0.09973114251911247
      },
      "dd": {
        "tvl": 2840.3688445187872,
        "category": "Dexs",
        "fees24h": 0,
        "liquidity_usd": 4041913.82,
        "pair_age_days": 558,
        "token_age_days": null,
        "flags": [
          {
            "k": "TVL sans revenu",
            "t": "warn"
          }
        ]
      }
    },
    {
      "id": 35347,
      "symbol": "MELANIA",
      "name": "Official Melania Meme",
      "price": 0.08015640021594149,
      "market_cap": 80156077.46393064,
      "volume_24h": 10702505.7964994,
      "pct_7d": -1.226632,
      "pct_30d": -15.50500966,
      "float_ratio": 0.9999999999999959,
      "score": 0.6458282519663205,
      "parts": {
        "float_quality": 0.9999999999999959,
        "momentum_24h": 0.07696004933333334,
        "momentum_7d": 0,
        "momentum_30d": 0,
        "volume_surge": 0.26704165510881966
      },
      "dd": {
        "tvl": 0,
        "category": "Meme",
        "fees24h": null,
        "liquidity_usd": 10363898.29,
        "pair_age_days": 518,
        "token_age_days": null,
        "flags": []
      }
    },
    {
      "id": 28850,
      "symbol": "NOT",
      "name": "Notcoin",
      "price": 0.00041522547469475136,
      "market_cap": 41285601.48842999,
      "volume_24h": 7890430.66851796,
      "pct_7d": -11.87527097,
      "pct_30d": -8.75506344,
      "float_ratio": 0.9704902864596566,
      "score": 0.644605723103845,
      "parts": {
        "float_quality": 0.9704902864596566,
        "momentum_24h": 0.066347803,
        "momentum_7d": 0,
        "momentum_30d": 0,
        "volume_surge": 0.38223644002033974
      },
      "dd": {
        "tvl": null,
        "category": null,
        "fees24h": null,
        "liquidity_usd": 187602.83,
        "pair_age_days": 767,
        "token_age_days": null,
        "flags": []
      }
    },
    {
      "id": 34118,
      "symbol": "BANANAS31",
      "name": "Banana For Scale",
      "price": 0.009290881736341593,
      "market_cap": 92908817.36341593,
      "volume_24h": 13788143.18223973,
      "pct_7d": -13.59072758,
      "pct_30d": -15.8230646,
      "float_ratio": 1,
      "score": 0.644521532746371,
      "parts": {
        "float_quality": 1,
        "momentum_24h": 0,
        "momentum_7d": 0,
        "momentum_30d": 0,
        "volume_surge": 0.29681021830913956
      },
      "dd": {
        "tvl": null,
        "category": null,
        "fees24h": null,
        "liquidity_usd": 4013611.11,
        "pair_age_days": 580,
        "token_age_days": null,
        "flags": []
      }
    },
    {
      "id": 4066,
      "symbol": "CHZ",
      "name": "Chiliz",
      "price": 0.020846774202367167,
      "market_cap": 217358178.74077934,
      "volume_24h": 32209860.1347123,
      "pct_7d": -18.248102,
      "pct_30d": -47.84789019,
      "float_ratio": 1,
      "score": 0.6444563811511216,
      "parts": {
        "float_quality": 1,
        "momentum_24h": 0,
        "momentum_7d": 0,
        "momentum_30d": 0,
        "volume_surge": 0.2963758743408103
      },
      "dd": {
        "tvl": null,
        "category": null,
        "fees24h": null,
        "liquidity_usd": null,
        "pair_age_days": null,
        "token_age_days": null,
        "flags": []
      }
    },
    {
      "id": 6210,
      "symbol": "SAND",
      "name": "The Sandbox",
      "price": 0.05526143503660036,
      "market_cap": 162338185.5736414,
      "volume_24h": 26901739.57220474,
      "pct_7d": 3.58379731,
      "pct_30d": -21.75390685,
      "float_ratio": 0.9792132341244408,
      "score": 0.6444097895884134,
      "parts": {
        "float_quality": 0.9792132341244408,
        "momentum_24h": 0,
        "momentum_7d": 0.0716759462,
        "momentum_30d": 0,
        "volume_surge": 0.3314283632916584
      },
      "dd": {
        "tvl": 0,
        "category": "Gaming",
        "fees24h": null,
        "liquidity_usd": null,
        "pair_age_days": null,
        "token_age_days": null,
        "flags": []
      }
    },
    {
      "id": 2765,
      "symbol": "XYO",
      "name": "XYO",
      "price": 0.003418252379699972,
      "market_cap": 47178320.06028561,
      "volume_24h": 7814437.77473611,
      "pct_7d": -5.23297169,
      "pct_30d": -18.33969451,
      "float_ratio": 0.9907492663084095,
      "score": 0.6441404205326346,
      "parts": {
        "float_quality": 0.9907492663084095,
        "momentum_24h": 0,
        "momentum_7d": 0,
        "momentum_30d": 0,
        "volume_surge": 0.33127240498392607
      },
      "dd": {
        "tvl": null,
        "category": null,
        "fees24h": null,
        "liquidity_usd": null,
        "pair_age_days": null,
        "token_age_days": null,
        "flags": []
      }
    },
    {
      "id": 32864,
      "symbol": "AUSD",
      "name": "AUSD",
      "price": 0.9998420625820821,
      "market_cap": 148195625.03079054,
      "volume_24h": 20966872.82036804,
      "pct_7d": 0.00426915,
      "pct_30d": 0.02948449,
      "float_ratio": 1,
      "score": 0.6424749670432309,
      "parts": {
        "float_quality": 1,
        "momentum_24h": 0,
        "momentum_7d": 0.000085383,
        "momentum_30d": 0.0002948449,
        "volume_surge": 0.2829621025048717
      },
      "dd": {
        "tvl": 0,
        "category": "CDP",
        "fees24h": null,
        "liquidity_usd": 1635579.67,
        "pair_age_days": 678,
        "token_age_days": null,
        "flags": []
      }
    },
    {
      "id": 10180,
      "symbol": "GOMINING",
      "name": "GoМining",
      "price": 0.2908206603460995,
      "market_cap": 117546755.84883432,
      "volume_24h": 12283427.47508114,
      "pct_7d": 4.26297497,
      "pct_30d": -1.12038994,
      "float_ratio": 0.9998096081905277,
      "score": 0.6416077166222515,
      "parts": {
        "float_quality": 0.9998096081905277,
        "momentum_24h": 0.024620452333333334,
        "momentum_7d": 0.08525949940000001,
        "momentum_30d": 0,
        "volume_surge": 0.20899645228623215
      },
      "dd": {
        "tvl": null,
        "category": null,
        "fees24h": null,
        "liquidity_usd": 84044.71,
        "pair_age_days": 836,
        "token_age_days": null,
        "flags": [
          {
            "k": "liquidité faible",
            "t": "bad"
          }
        ]
      }
    },
    {
      "id": 2130,
      "symbol": "ENJ",
      "name": "Enjin Coin",
      "price": 0.03289129572922902,
      "market_cap": 65007932.06681012,
      "volume_24h": 7381033.30284527,
      "pct_7d": 6.54204917,
      "pct_30d": -22.51853363,
      "float_ratio": 0.9883934505651351,
      "score": 0.6401823195651897,
      "parts": {
        "float_quality": 0.9883934505651351,
        "momentum_24h": 0,
        "momentum_7d": 0.1308409834,
        "momentum_30d": 0,
        "volume_surge": 0.22708100590739036
      },
      "dd": {
        "tvl": null,
        "category": null,
        "fees24h": null,
        "liquidity_usd": 194316365.61,
        "pair_age_days": 426,
        "token_age_days": null,
        "flags": []
      }
    },
    {
      "id": 32796,
      "symbol": "EURCV",
      "name": "EUR CoinVertible",
      "price": 1.145229590646982,
      "market_cap": 135431269.71872422,
      "volume_24h": 17958767.86532709,
      "pct_7d": -1.31609455,
      "pct_30d": -1.17062379,
      "float_ratio": 1,
      "score": 0.63978128810863,
      "parts": {
        "float_quality": 1,
        "momentum_24h": 0,
        "momentum_7d": 0,
        "momentum_30d": 0,
        "volume_surge": 0.2652085873908657
      },
      "dd": {
        "tvl": null,
        "category": null,
        "fees24h": null,
        "liquidity_usd": null,
        "pair_age_days": null,
        "token_age_days": null,
        "flags": []
      }
    },
    {
      "id": 32372,
      "symbol": "XUSD",
      "name": "StraitsX USD",
      "price": 0.9996206743270668,
      "market_cap": 46546972.399280936,
      "volume_24h": 6041182.57833903,
      "pct_7d": -0.04603566,
      "pct_30d": -0.01690391,
      "float_ratio": 1,
      "score": 0.6389360398772083,
      "parts": {
        "float_quality": 1,
        "momentum_24h": 0,
        "momentum_7d": 0,
        "momentum_30d": 0,
        "volume_surge": 0.25957359918138756
      },
      "dd": {
        "tvl": 24790.63946145722,
        "category": "Algo-Stables",
        "fees24h": null,
        "liquidity_usd": null,
        "pair_age_days": null,
        "token_age_days": null,
        "flags": [
          {
            "k": "TVL sans revenu",
            "t": "warn"
          }
        ]
      }
    },
    {
      "id": 27048,
      "symbol": "APEPE",
      "name": "Ape and Pepe",
      "price": 0.0000010570991412693279,
      "market_cap": 221990819.66655886,
      "volume_24h": 26797590.20937241,
      "pct_7d": -2.29155901,
      "pct_30d": -5.77584796,
      "float_ratio": 1,
      "score": 0.6362144573135372,
      "parts": {
        "float_quality": 1,
        "momentum_24h": 0,
        "momentum_7d": 0,
        "momentum_30d": 0,
        "volume_surge": 0.2414297154235811
      },
      "dd": {
        "tvl": null,
        "category": null,
        "fees24h": null,
        "liquidity_usd": 13950.04,
        "pair_age_days": 1109,
        "token_age_days": null,
        "flags": [
          {
            "k": "liquidité faible",
            "t": "bad"
          }
        ]
      }
    },
    {
      "id": 131,
      "symbol": "DASH",
      "name": "Dash",
      "price": 35.12177724356796,
      "market_cap": 447638459.4333291,
      "volume_24h": 53520785.33384214,
      "pct_7d": -10.09565399,
      "pct_30d": -20.68837978,
      "float_ratio": 1.0000001996574486,
      "score": 0.6358687580608656,
      "parts": {
        "float_quality": 1,
        "momentum_24h": 0,
        "momentum_7d": 0,
        "momentum_30d": 0,
        "volume_surge": 0.23912505373910342
      },
      "dd": {
        "tvl": null,
        "category": null,
        "fees24h": null,
        "liquidity_usd": 1030857894.8,
        "pair_age_days": 48,
        "token_age_days": null,
        "flags": []
      }
    },
    {
      "id": 37545,
      "symbol": "BNKR",
      "name": "BankrCoin",
      "price": 0.00044172990133788977,
      "market_cap": 43863779.20285231,
      "volume_24h": 5831476.75816382,
      "pct_7d": -7.86243731,
      "pct_30d": -7.00920919,
      "float_ratio": 0.9929999999999967,
      "score": 0.6356835453588847,
      "parts": {
        "float_quality": 0.9929999999999967,
        "momentum_24h": 0,
        "momentum_7d": 0,
        "momentum_30d": 0,
        "volume_surge": 0.2658903023925772
      },
      "dd": {
        "tvl": 0,
        "category": "Interface",
        "fees24h": 33815,
        "liquidity_usd": 2210243.08,
        "pair_age_days": 566,
        "token_age_days": null,
        "flags": [
          {
            "k": "revenu réel",
            "t": "ok"
          }
        ]
      }
    }
  ]
}