{
  "updated_at": "2026-07-16T11:27:15.751Z",
  "source": "coinmarketcap",
  "note": "Triage, pas un prédicteur. Le tracker dit si le score vaut quelque chose.",
  "weights_mode": "appris",
  "weights": {
    "float_quality": 0.387,
    "momentum_24h": 0.075,
    "momentum_7d": 0.1,
    "momentum_30d": 0.075,
    "volume_surge": 0.363
  },
  "dd_status": {
    "coingecko": true,
    "cg": 1,
    "dd": 31
  },
  "count": 50,
  "candidates": [
    {
      "id": 40809,
      "symbol": "CASHCAT",
      "name": "Cash Cat",
      "price": 0.09706705458773386,
      "market_cap": 97067054.58773386,
      "volume_24h": 66734138.27768774,
      "pct_7d": -4.15668429,
      "pct_30d": 12046.34178202,
      "float_ratio": 1,
      "score": 0.825,
      "parts": {
        "float_quality": 1,
        "momentum_24h": 0,
        "momentum_7d": 0,
        "momentum_30d": 1,
        "volume_surge": 1
      },
      "dd": {
        "tvl": null,
        "category": "Solana Ecosystem",
        "fees24h": null,
        "liquidity_usd": null,
        "pair_age_days": null,
        "token_age_days": null,
        "flags": []
      }
    },
    {
      "id": 36296,
      "symbol": "BANK",
      "name": "Lorenzo Protocol",
      "price": 0.0614149341356669,
      "market_cap": 41820175.09851803,
      "volume_24h": 38221104.8553469,
      "pct_7d": 75.16781754,
      "pct_30d": 49.93997577,
      "float_ratio": 0.5617448117965265,
      "score": 0.7928502239927557,
      "parts": {
        "float_quality": 0.5617448117965265,
        "momentum_24h": 1,
        "momentum_7d": 1,
        "momentum_30d": 0.49939975769999995,
        "volume_surge": 1
      },
      "dd": {
        "tvl": 210480.2172214313,
        "category": "Reserve Currency",
        "fees24h": 0,
        "liquidity_usd": 69198.88,
        "pair_age_days": 442,
        "token_age_days": null,
        "flags": [
          {
            "k": "TVL sans revenu",
            "t": "warn"
          },
          {
            "k": "liquidité faible",
            "t": "bad"
          }
        ]
      }
    },
    {
      "id": 26081,
      "symbol": "FDUSD",
      "name": "First Digital USD",
      "price": 0.9971528160126181,
      "market_cap": 346167116.1118103,
      "volume_24h": 195882481.9304839,
      "pct_7d": 0.02220837,
      "pct_30d": -0.12534853,
      "float_ratio": 1,
      "score": 0.75004441674,
      "parts": {
        "float_quality": 1,
        "momentum_24h": 0,
        "momentum_7d": 0.0004441674,
        "momentum_30d": 0,
        "volume_surge": 1
      },
      "dd": {
        "tvl": null,
        "category": "Stablecoins",
        "fees24h": null,
        "liquidity_usd": null,
        "pair_age_days": null,
        "token_age_days": null,
        "flags": []
      }
    },
    {
      "id": 40212,
      "symbol": "MUB",
      "name": "Micron Technology Tokenized bStocks",
      "price": 867.421376278114,
      "market_cap": 62850178.08935337,
      "volume_24h": 34423036.65426457,
      "pct_7d": -12.08901619,
      "pct_30d": -23.26873418,
      "float_ratio": 1,
      "score": 0.75,
      "parts": {
        "float_quality": 1,
        "momentum_24h": 0,
        "momentum_7d": 0,
        "momentum_30d": 0,
        "volume_surge": 1
      },
      "dd": {
        "tvl": null,
        "category": "Tokenized Assets",
        "fees24h": null,
        "liquidity_usd": null,
        "pair_age_days": null,
        "token_age_days": null,
        "flags": []
      }
    },
    {
      "id": 40216,
      "symbol": "SNDKB",
      "name": "SanDisk Tokenized bStocks",
      "price": 1508.107114549984,
      "market_cap": 46938904.06304211,
      "volume_24h": 27216614.26827346,
      "pct_7d": -15.59536387,
      "pct_30d": -30.17488912,
      "float_ratio": 1,
      "score": 0.75,
      "parts": {
        "float_quality": 1,
        "momentum_24h": 0,
        "momentum_7d": 0,
        "momentum_30d": 0,
        "volume_surge": 1
      },
      "dd": {
        "tvl": null,
        "category": "Tokenized Assets",
        "fees24h": null,
        "liquidity_usd": null,
        "pair_age_days": null,
        "token_age_days": null,
        "flags": []
      }
    },
    {
      "id": 25028,
      "symbol": "ORDI",
      "name": "ORDI",
      "price": 3.712060512803413,
      "market_cap": 77953270.76887168,
      "volume_24h": 34269626.33457099,
      "pct_7d": 6.48009791,
      "pct_30d": 5.54662377,
      "float_ratio": 1,
      "score": 0.7450063910525951,
      "parts": {
        "float_quality": 1,
        "momentum_24h": 0.289651762,
        "momentum_7d": 0.12960195819999998,
        "momentum_30d": 0.055466237700000004,
        "volume_surge": 0.8792351108955788
      },
      "dd": {
        "tvl": null,
        "category": "Solana Ecosystem",
        "fees24h": null,
        "liquidity_usd": null,
        "pair_age_days": null,
        "token_age_days": null,
        "flags": []
      }
    },
    {
      "id": 23121,
      "symbol": "BLUR",
      "name": "Blur",
      "price": 0.01689355412586154,
      "market_cap": 48047133.743596315,
      "volume_24h": 25745774.2128331,
      "pct_7d": -8.94963026,
      "pct_30d": -9.07748314,
      "float_ratio": 0.9480368150209284,
      "score": 0.7401200551380993,
      "parts": {
        "float_quality": 0.9480368150209284,
        "momentum_24h": 0.13639743633333332,
        "momentum_7d": 0,
        "momentum_30d": 0,
        "volume_surge": 1
      },
      "dd": {
        "tvl": 14079094.06419687,
        "category": "NFT Marketplace",
        "fees24h": 0,
        "liquidity_usd": null,
        "pair_age_days": null,
        "token_age_days": null,
        "flags": [
          {
            "k": "TVL sans revenu",
            "t": "warn"
          }
        ]
      }
    },
    {
      "id": 12147,
      "symbol": "SYN",
      "name": "Synapse",
      "price": 0.23220010464960347,
      "market_cap": 54852360.518309034,
      "volume_24h": 20889793.34497032,
      "pct_7d": -33.52609011,
      "pct_30d": 358.87583768,
      "float_ratio": 0.9445062650754027,
      "score": 0.7170113870223057,
      "parts": {
        "float_quality": 0.9445062650754027,
        "momentum_24h": 0,
        "momentum_7d": 0,
        "momentum_30d": 1,
        "volume_surge": 0.7616734502427682
      },
      "dd": {
        "tvl": 11523416.034313885,
        "category": "Cross Chain Bridge",
        "fees24h": 28,
        "liquidity_usd": null,
        "pair_age_days": null,
        "token_age_days": null,
        "flags": [
          {
            "k": "TVL sans revenu",
            "t": "warn"
          }
        ]
      }
    },
    {
      "id": 109,
      "symbol": "DGB",
      "name": "DigiByte",
      "price": 0.003462527036981906,
      "market_cap": 63652867.84871783,
      "volume_24h": 11173964.2186501,
      "pct_7d": 42.70454141,
      "pct_30d": 27.36053517,
      "float_ratio": 1,
      "score": 0.6953753997848426,
      "parts": {
        "float_quality": 1,
        "momentum_24h": 1,
        "momentum_7d": 0.8540908281999999,
        "momentum_30d": 0.2736053517,
        "volume_surge": 0.35109067654915344
      },
      "dd": {
        "tvl": null,
        "category": "Internet of Things (IOT)",
        "fees24h": null,
        "liquidity_usd": 164316317.65,
        "pair_age_days": 279,
        "token_age_days": 4570,
        "flags": []
      }
    },
    {
      "id": 17751,
      "symbol": "T",
      "name": "Threshold",
      "price": 0.003930001959633495,
      "market_cap": 43839171.85971164,
      "volume_24h": 16641416.80279836,
      "pct_7d": 15.54553153,
      "pct_30d": 1.81291788,
      "float_ratio": 1,
      "score": 0.695041463755665,
      "parts": {
        "float_quality": 1,
        "momentum_24h": 0,
        "momentum_7d": 0.3109106306,
        "momentum_30d": 0.0181291788,
        "volume_surge": 0.7592030641478373
      },
      "dd": {
        "tvl": 326800130.63414985,
        "category": "Decentralized BTC",
        "fees24h": 6892,
        "liquidity_usd": null,
        "pair_age_days": null,
        "token_age_days": null,
        "flags": [
          {
            "k": "revenu réel",
            "t": "ok"
          }
        ]
      }
    },
    {
      "id": 1757,
      "symbol": "FUN",
      "name": "FUNToken",
      "price": 0.00370480461806936,
      "market_cap": 40034865.80782178,
      "volume_24h": 12543923.98868997,
      "pct_7d": 10.96804863,
      "pct_30d": 51.54004112,
      "float_ratio": 1,
      "score": 0.6820498779744768,
      "parts": {
        "float_quality": 1,
        "momentum_24h": 0.09313074733333333,
        "momentum_7d": 0.2193609726,
        "momentum_30d": 0.5154004112,
        "volume_surge": 0.6266499829875394
      },
      "dd": {
        "tvl": 2754169.965687874,
        "category": "Prediction Market",
        "fees24h": 2607,
        "liquidity_usd": null,
        "pair_age_days": null,
        "token_age_days": null,
        "flags": [
          {
            "k": "revenu réel",
            "t": "ok"
          }
        ]
      }
    },
    {
      "id": 10791,
      "symbol": "XEC",
      "name": "eCash",
      "price": 0.000006303843076641837,
      "market_cap": 126433058.12187809,
      "volume_24h": 38725909.31244691,
      "pct_7d": 23.2367321,
      "pct_30d": 10.5896624,
      "float_ratio": 1,
      "score": 0.6637864309562818,
      "parts": {
        "float_quality": 1,
        "momentum_24h": 0,
        "momentum_7d": 0.46473464200000003,
        "momentum_30d": 0.105896624,
        "volume_surge": 0.6125915150310793
      },
      "dd": {
        "tvl": null,
        "category": "Smart Contract Platform",
        "fees24h": null,
        "liquidity_usd": 180257080.55,
        "pair_age_days": 332,
        "token_age_days": null,
        "flags": []
      }
    },
    {
      "id": 7080,
      "symbol": "GALA",
      "name": "Gala",
      "price": 0.0020065477738813184,
      "market_cap": 97960725.18522903,
      "volume_24h": 32962216.78610405,
      "pct_7d": -5.00242914,
      "pct_30d": -26.92713886,
      "float_ratio": 1,
      "score": 0.6312873849847724,
      "parts": {
        "float_quality": 1,
        "momentum_24h": 0,
        "momentum_7d": 0,
        "momentum_30d": 0,
        "volume_surge": 0.6729680027128718
      },
      "dd": {
        "tvl": null,
        "category": null,
        "fees24h": null,
        "liquidity_usd": null,
        "pair_age_days": null,
        "token_age_days": null,
        "flags": []
      }
    },
    {
      "id": 28752,
      "symbol": "WIF",
      "name": "dogwifhat",
      "price": 0.1513169616635026,
      "market_cap": 151141277.76569867,
      "volume_24h": 50758999.18488197,
      "pct_7d": -4.23571422,
      "pct_30d": -11.11446257,
      "float_ratio": 1,
      "score": 0.6308184588154091,
      "parts": {
        "float_quality": 1,
        "momentum_24h": 0,
        "momentum_7d": 0,
        "momentum_30d": 0,
        "volume_surge": 0.6716761950837716
      },
      "dd": {
        "tvl": null,
        "category": null,
        "fees24h": null,
        "liquidity_usd": 4184268.97,
        "pair_age_days": 968,
        "token_age_days": null,
        "flags": []
      }
    },
    {
      "id": 2943,
      "symbol": "RPL",
      "name": "Rocket Pool",
      "price": 1.838855032938436,
      "market_cap": 41594160.165745586,
      "volume_24h": 10706370.68955219,
      "pct_7d": 7.35088969,
      "pct_30d": 28.29217306,
      "float_ratio": 1,
      "score": 0.6221505871055116,
      "parts": {
        "float_quality": 1,
        "momentum_24h": 0.164755825,
        "momentum_7d": 0.1470177938,
        "momentum_30d": 0.2829217306,
        "volume_surge": 0.514801628252098
      },
      "dd": {
        "tvl": 996783007.1680665,
        "category": "Liquid Staking",
        "fees24h": 2335,
        "liquidity_usd": null,
        "pair_age_days": null,
        "token_age_days": null,
        "flags": [
          {
            "k": "revenu réel",
            "t": "ok"
          }
        ]
      }
    },
    {
      "id": 36195,
      "symbol": "AGT",
      "name": "Alaya Governance Token",
      "price": 0.01344999087267876,
      "market_cap": 39198787.01154431,
      "volume_24h": 20218182.16292148,
      "pct_7d": 10.47971708,
      "pct_30d": -4.18257848,
      "float_ratio": 0.5828819868,
      "score": 0.6148070760516,
      "parts": {
        "float_quality": 0.5828819868,
        "momentum_24h": 0.07029750666666666,
        "momentum_7d": 0.2095943416,
        "momentum_30d": 0,
        "volume_surge": 1
      },
      "dd": {
        "tvl": 0,
        "category": "Decentralized AI",
        "fees24h": null,
        "liquidity_usd": null,
        "pair_age_days": null,
        "token_age_days": null,
        "flags": []
      }
    },
    {
      "id": 29743,
      "symbol": "BRETT",
      "name": "Brett (Based)",
      "price": 0.00518268049826119,
      "market_cap": 51826792.25769642,
      "volume_24h": 16029303.81138238,
      "pct_7d": -0.10117622,
      "pct_30d": -18.53980093,
      "float_ratio": 1,
      "score": 0.6115416715971929,
      "parts": {
        "float_quality": 1,
        "momentum_24h": 0,
        "momentum_7d": 0,
        "momentum_30d": 0,
        "volume_surge": 0.6185720980638922
      },
      "dd": {
        "tvl": null,
        "category": null,
        "fees24h": null,
        "liquidity_usd": null,
        "pair_age_days": null,
        "token_age_days": null,
        "flags": []
      }
    },
    {
      "id": 32197,
      "symbol": "ME",
      "name": "Magic Eden",
      "price": 0.06634846481927405,
      "market_cap": 38631165.526741676,
      "volume_24h": 185819195.4253457,
      "pct_7d": 8.39283729,
      "pct_30d": 3.78170545,
      "float_ratio": 0.5822518999283599,
      "score": 0.6079534389397753,
      "parts": {
        "float_quality": 0.5822518999283599,
        "momentum_24h": 0,
        "momentum_7d": 0.16785674579999998,
        "momentum_30d": 0.0378170545,
        "volume_surge": 1
      },
      "dd": {
        "tvl": 119214.65969723518,
        "category": "NFT Marketplace",
        "fees24h": null,
        "liquidity_usd": 599368.04,
        "pair_age_days": 582,
        "token_age_days": null,
        "flags": [
          {
            "k": "TVL sans revenu",
            "t": "warn"
          }
        ]
      }
    },
    {
      "id": 29587,
      "symbol": "W",
      "name": "Wormhole",
      "price": 0.009468710175334521,
      "market_cap": 58413273.67002141,
      "volume_24h": 115999549.3622124,
      "pct_7d": -1.98795086,
      "pct_30d": -4.86623563,
      "float_ratio": 0.6169084552,
      "score": 0.6017435721624,
      "parts": {
        "float_quality": 0.6169084552,
        "momentum_24h": 0,
        "momentum_7d": 0,
        "momentum_30d": 0,
        "volume_surge": 1
      },
      "dd": {
        "tvl": 2388214386.791208,
        "category": "Bridge",
        "fees24h": 463,
        "liquidity_usd": null,
        "pair_age_days": null,
        "token_age_days": null,
        "flags": [
          {
            "k": "TVL sans revenu",
            "t": "warn"
          }
        ]
      }
    },
    {
      "id": 40588,
      "symbol": "ANSEM",
      "name": "The Black Bull",
      "price": 0.17601315108115345,
      "market_cap": 73161419.38651048,
      "volume_24h": 52196018.28966026,
      "pct_7d": -44.70304604,
      "pct_30d": 494365.8702583,
      "float_ratio": 0.4156823624927154,
      "score": 0.5988690742846808,
      "parts": {
        "float_quality": 0.4156823624927154,
        "momentum_24h": 0,
        "momentum_7d": 0,
        "momentum_30d": 1,
        "volume_surge": 1
      },
      "dd": {
        "tvl": null,
        "category": null,
        "fees24h": null,
        "liquidity_usd": 1885256.77,
        "pair_age_days": 29,
        "token_age_days": null,
        "flags": []
      }
    },
    {
      "id": 8536,
      "symbol": "MASK",
      "name": "Mask Network",
      "price": 0.392918095523931,
      "market_cap": 39291809.5523931,
      "volume_24h": 10468486.81149168,
      "pct_7d": -4.87948635,
      "pct_30d": 2.74725677,
      "float_ratio": 1,
      "score": 0.582488068123956,
      "parts": {
        "float_quality": 1,
        "momentum_24h": 0,
        "momentum_7d": 0,
        "momentum_30d": 0.0274725677,
        "volume_surge": 0.5328584725797688
      },
      "dd": {
        "tvl": null,
        "category": null,
        "fees24h": null,
        "liquidity_usd": null,
        "pair_age_days": null,
        "token_age_days": null,
        "flags": []
      }
    },
    {
      "id": 8000,
      "symbol": "LDO",
      "name": "Lido DAO",
      "price": 0.36177175457581523,
      "market_cap": 302572266.7553428,
      "volume_24h": 75645552.60408682,
      "pct_7d": 13.5593241,
      "pct_30d": 30.57398537,
      "float_ratio": 0.8363623277060835,
      "score": 0.5814060460213828,
      "parts": {
        "float_quality": 0.8363623277060835,
        "momentum_24h": 0.34904964266666666,
        "momentum_7d": 0.271186482,
        "momentum_30d": 0.3057398537,
        "volume_surge": 0.5000164318777645
      },
      "dd": {
        "tvl": 17313489763.668125,
        "category": "Liquid Staking",
        "fees24h": 1156912,
        "liquidity_usd": null,
        "pair_age_days": null,
        "token_age_days": null,
        "flags": [
          {
            "k": "revenu réel",
            "t": "ok"
          }
        ]
      }
    },
    {
      "id": 33093,
      "symbol": "MOODENG",
      "name": "Moo Deng (moodengsol.com)",
      "price": 0.038427240109949676,
      "market_cap": 38041883.72136655,
      "volume_24h": 9716851.99740113,
      "pct_7d": -3.45832928,
      "pct_30d": -8.73241792,
      "float_ratio": 1,
      "score": 0.5724386234336507,
      "parts": {
        "float_quality": 1,
        "momentum_24h": 0,
        "momentum_7d": 0,
        "momentum_30d": 0,
        "volume_surge": 0.5108502022965585
      },
      "dd": {
        "tvl": null,
        "category": null,
        "fees24h": null,
        "liquidity_usd": 2181328.72,
        "pair_age_days": 673,
        "token_age_days": null,
        "flags": []
      }
    },
    {
      "id": 40213,
      "symbol": "CRCLB",
      "name": "Circle Internet Group Tokenized bStocks",
      "price": 64.3670840504604,
      "market_cap": 48964093.582734324,
      "volume_24h": 12035907.97694898,
      "pct_7d": 0.44504174,
      "pct_30d": -24.05583496,
      "float_ratio": 1,
      "score": 0.5705984957290402,
      "parts": {
        "float_quality": 1,
        "momentum_24h": 0.05666263833333333,
        "momentum_7d": 0.0089008348,
        "momentum_30d": 0,
        "volume_surge": 0.49162180268330635
      },
      "dd": {
        "tvl": null,
        "category": null,
        "fees24h": null,
        "liquidity_usd": null,
        "pair_age_days": null,
        "token_age_days": null,
        "flags": []
      }
    },
    {
      "id": 28782,
      "symbol": "POPCAT",
      "name": "Popcat (SOL)",
      "price": 0.04423321631526397,
      "market_cap": 43345735.92146764,
      "volume_24h": 10453557.12335595,
      "pct_7d": -3.48640917,
      "pct_30d": -1.09552131,
      "float_ratio": 1,
      "score": 0.5620871754791851,
      "parts": {
        "float_quality": 1,
        "momentum_24h": 0,
        "momentum_7d": 0,
        "momentum_30d": 0,
        "volume_surge": 0.4823338167470662
      },
      "dd": {
        "tvl": null,
        "category": null,
        "fees24h": null,
        "liquidity_usd": 2939488.94,
        "pair_age_days": 946,
        "token_age_days": null,
        "flags": []
      }
    },
    {
      "id": 27659,
      "symbol": "MOG",
      "name": "Mog Coin",
      "price": 1.0458386367402919e-7,
      "market_cap": 40847060.93999433,
      "volume_24h": 9338752.93728803,
      "pct_7d": 1.50726267,
      "pct_30d": -13.17253047,
      "float_ratio": 1,
      "score": 0.555997939481621,
      "parts": {
        "float_quality": 1,
        "momentum_24h": 0,
        "momentum_7d": 0.030145253400000002,
        "momentum_30d": 0,
        "volume_surge": 0.45725458441217903
      },
      "dd": {
        "tvl": null,
        "category": null,
        "fees24h": null,
        "liquidity_usd": 4588431.19,
        "pair_age_days": 1092,
        "token_age_days": null,
        "flags": []
      }
    },
    {
      "id": 1974,
      "symbol": "PRO",
      "name": "Propy",
      "price": 0.3761809744667177,
      "market_cap": 37618097.44667177,
      "volume_24h": 6329726.2638829,
      "pct_7d": -3.51581837,
      "pct_30d": 23.61154421,
      "float_ratio": 1,
      "score": 0.5448244339944894,
      "parts": {
        "float_quality": 1,
        "momentum_24h": 0.23942647733333333,
        "momentum_7d": 0,
        "momentum_30d": 0.23611544210000002,
        "volume_surge": 0.3365255923884007
      },
      "dd": {
        "tvl": null,
        "category": null,
        "fees24h": null,
        "liquidity_usd": null,
        "pair_age_days": null,
        "token_age_days": null,
        "flags": []
      }
    },
    {
      "id": 40217,
      "symbol": "SPCXB",
      "name": "SpaceX Tokenized bStocks",
      "price": 134.98663052765576,
      "market_cap": 89463146.83380277,
      "volume_24h": 19301170.61283307,
      "pct_7d": -9.7678644,
      "pct_30d": -35.01492987,
      "float_ratio": 1,
      "score": 0.5436304155491909,
      "parts": {
        "float_quality": 1,
        "momentum_24h": 0,
        "momentum_7d": 0,
        "momentum_30d": 0,
        "volume_surge": 0.4314887480693964
      },
      "dd": {
        "tvl": null,
        "category": null,
        "fees24h": null,
        "liquidity_usd": 488087.23,
        "pair_age_days": 33,
        "token_age_days": null,
        "flags": []
      }
    },
    {
      "id": 3773,
      "symbol": "FET",
      "name": "Artificial Superintelligence Alliance",
      "price": 0.1579607794478092,
      "market_cap": 353900137.21390086,
      "volume_24h": 109063772.0564724,
      "pct_7d": -0.78222477,
      "pct_30d": -25.50165059,
      "float_ratio": 0.8253916837117377,
      "score": 0.5431628568529326,
      "parts": {
        "float_quality": 0.8253916837117377,
        "momentum_24h": 0,
        "momentum_7d": 0,
        "momentum_30d": 0,
        "volume_surge": 0.6163533753622319
      },
      "dd": {
        "tvl": null,
        "category": null,
        "fees24h": null,
        "liquidity_usd": 2819774341.58,
        "pair_age_days": 459,
        "token_age_days": null,
        "flags": []
      }
    },
    {
      "id": 21846,
      "symbol": "ID",
      "name": "SPACE ID",
      "price": 0.0355951720130768,
      "market_cap": 70057530.76827714,
      "volume_24h": 11837533.73121293,
      "pct_7d": -4.37407746,
      "pct_30d": 29.16032388,
      "float_ratio": 0.9866321854790163,
      "score": 0.5414686523269597,
      "parts": {
        "float_quality": 0.9866321854790163,
        "momentum_24h": 0.20133916966666668,
        "momentum_7d": 0,
        "momentum_30d": 0.2916032388,
        "volume_surge": 0.3379375093982931
      },
      "dd": {
        "tvl": null,
        "category": null,
        "fees24h": null,
        "liquidity_usd": null,
        "pair_age_days": null,
        "token_age_days": null,
        "flags": []
      }
    },
    {
      "id": 38869,
      "symbol": "US",
      "name": "Talus",
      "price": 0.041934884110348944,
      "market_cap": 92256745.04276767,
      "volume_24h": 26234940.53558682,
      "pct_7d": 118.23896774,
      "pct_30d": 209.81780177,
      "float_ratio": 0.22,
      "score": 0.5331538129862585,
      "parts": {
        "float_quality": 0.22,
        "momentum_24h": 0.8874941203333333,
        "momentum_7d": 1,
        "momentum_30d": 1,
        "volume_surge": 0.5687376142183431
      },
      "dd": {
        "tvl": 323752.9511375787,
        "category": "Dexs",
        "fees24h": 97,
        "liquidity_usd": 207079.17,
        "pair_age_days": 27,
        "token_age_days": null,
        "flags": [
          {
            "k": "TVL sans revenu",
            "t": "warn"
          }
        ]
      }
    },
    {
      "id": 4066,
      "symbol": "CHZ",
      "name": "Chiliz",
      "price": 0.016523634646934317,
      "market_cap": 174405882.4743586,
      "volume_24h": 34820635.94973188,
      "pct_7d": -3.00645932,
      "pct_30d": -32.9193208,
      "float_ratio": 1,
      "score": 0.5319479876530083,
      "parts": {
        "float_quality": 1,
        "momentum_24h": 0,
        "momentum_7d": 0,
        "momentum_30d": 0,
        "volume_surge": 0.39930575111021566
      },
      "dd": {
        "tvl": null,
        "category": null,
        "fees24h": null,
        "liquidity_usd": null,
        "pair_age_days": null,
        "token_age_days": null,
        "flags": []
      }
    },
    {
      "id": 38273,
      "symbol": "USDon",
      "name": "U.S. Dollar Tokenized Currency (Ondo)",
      "price": 0.9993926674700006,
      "market_cap": 90807340.54185948,
      "volume_24h": 17994607.35477368,
      "pct_7d": 0.02386155,
      "pct_30d": -0.01251286,
      "float_ratio": 1,
      "score": 0.5309136799886234,
      "parts": {
        "float_quality": 1,
        "momentum_24h": 0,
        "momentum_7d": 0.000477231,
        "momentum_30d": 0,
        "volume_surge": 0.39632495010640034
      },
      "dd": {
        "tvl": null,
        "category": null,
        "fees24h": null,
        "liquidity_usd": null,
        "pair_age_days": null,
        "token_age_days": null,
        "flags": []
      }
    },
    {
      "id": 18876,
      "symbol": "APE",
      "name": "ApeCoin",
      "price": 0.15200500708097545,
      "market_cap": 152005007.08097544,
      "volume_24h": 24972739.53005381,
      "pct_7d": -6.69768885,
      "pct_30d": 17.46378336,
      "float_ratio": 1,
      "score": 0.5285450664584148,
      "parts": {
        "float_quality": 1,
        "momentum_24h": 0.12231290466666667,
        "momentum_7d": 0,
        "momentum_30d": 0.17463783360000001,
        "volume_surge": 0.3285778542380573
      },
      "dd": {
        "tvl": 0,
        "category": "Yield",
        "fees24h": null,
        "liquidity_usd": 338958.41,
        "pair_age_days": 525,
        "token_age_days": null,
        "flags": []
      }
    },
    {
      "id": 38014,
      "symbol": "MUon",
      "name": "Micron Technology Tokenized Stock (Ondo)",
      "price": 869.8023243846656,
      "market_cap": 45186766.79724781,
      "volume_24h": 8623103.12572943,
      "pct_7d": -11.76402481,
      "pct_30d": -23.06572592,
      "float_ratio": 1,
      "score": 0.5255443861776998,
      "parts": {
        "float_quality": 1,
        "momentum_24h": 0,
        "momentum_7d": 0,
        "momentum_30d": 0,
        "volume_surge": 0.3816649756961428
      },
      "dd": {
        "tvl": null,
        "category": null,
        "fees24h": null,
        "liquidity_usd": null,
        "pair_age_days": null,
        "token_age_days": null,
        "flags": []
      }
    },
    {
      "id": 10529,
      "symbol": "SUN",
      "name": "Sun [New]",
      "price": 0.01800853893557245,
      "market_cap": 346325940.33978254,
      "volume_24h": 63642721.48006733,
      "pct_7d": -4.20674255,
      "pct_30d": 6.12428322,
      "float_ratio": 1,
      "score": 0.5250068855265124,
      "parts": {
        "float_quality": 1,
        "momentum_24h": 0,
        "momentum_7d": 0,
        "momentum_30d": 0.0612428322,
        "volume_surge": 0.36753077992152167
      },
      "dd": {
        "tvl": 212619764.241987,
        "category": "Dexs",
        "fees24h": 18854,
        "liquidity_usd": 16785973.97,
        "pair_age_days": 1673,
        "token_age_days": null,
        "flags": [
          {
            "k": "revenu réel",
            "t": "ok"
          }
        ]
      }
    },
    {
      "id": 37013,
      "symbol": "GOOGLX",
      "name": "Alphabet tokenized stock (xStock)",
      "price": 376.79440171828975,
      "market_cap": 145337394.57017925,
      "volume_24h": 22683191.84692159,
      "pct_7d": 4.33961239,
      "pct_30d": 1.96157088,
      "float_ratio": 1,
      "score": 0.5232541068535014,
      "parts": {
        "float_quality": 1,
        "momentum_24h": 0.17059949800000002,
        "momentum_7d": 0.0867922478,
        "momentum_30d": 0.0196157088,
        "volume_surge": 0.31214529356336473
      },
      "dd": {
        "tvl": null,
        "category": null,
        "fees24h": null,
        "liquidity_usd": null,
        "pair_age_days": null,
        "token_age_days": null,
        "flags": []
      }
    },
    {
      "id": 4846,
      "symbol": "KAVA",
      "name": "Kava",
      "price": 0.04520194554736068,
      "market_cap": 48946791.53694038,
      "volume_24h": 8729649.45335618,
      "pct_7d": 2.18953725,
      "pct_30d": -4.91802285,
      "float_ratio": 1,
      "score": 0.5226287110537596,
      "parts": {
        "float_quality": 1,
        "momentum_24h": 0.023569293333333335,
        "momentum_7d": 0.043790745,
        "momentum_30d": 0,
        "volume_surge": 0.3566995579993378
      },
      "dd": {
        "tvl": null,
        "category": null,
        "fees24h": null,
        "liquidity_usd": null,
        "pair_age_days": null,
        "token_age_days": null,
        "flags": []
      }
    },
    {
      "id": 4944,
      "symbol": "TRB",
      "name": "Tellor",
      "price": 14.97557206336041,
      "market_cap": 41822040.4921936,
      "volume_24h": 7864805.320513,
      "pct_7d": -4.69858104,
      "pct_30d": 2.92363721,
      "float_ratio": 0.9710623365297754,
      "score": 0.518240548313998,
      "parts": {
        "float_quality": 0.9710623365297754,
        "momentum_24h": 0.049592461000000004,
        "momentum_7d": 0,
        "momentum_30d": 0.029236372099999998,
        "volume_surge": 0.3761081586624653
      },
      "dd": {
        "tvl": null,
        "category": null,
        "fees24h": null,
        "liquidity_usd": null,
        "pair_age_days": null,
        "token_age_days": null,
        "flags": []
      }
    },
    {
      "id": 27750,
      "symbol": "TOSHI",
      "name": "Toshi",
      "price": 0.00011186945449371516,
      "market_cap": 47060051.25251677,
      "volume_24h": 7937416.19556748,
      "pct_7d": -0.89336252,
      "pct_30d": -16.15718667,
      "float_ratio": 0.9999509255718483,
      "score": 0.513899076632419,
      "parts": {
        "float_quality": 0.9999509255718483,
        "momentum_24h": 0.059556996333333334,
        "momentum_7d": 0,
        "momentum_30d": 0,
        "volume_surge": 0.3373313876339218
      },
      "dd": {
        "tvl": null,
        "category": null,
        "fees24h": null,
        "liquidity_usd": 372831.88,
        "pair_age_days": 347,
        "token_age_days": null,
        "flags": []
      }
    },
    {
      "id": 36133,
      "symbol": "HOME",
      "name": "Defi App",
      "price": 0.013276055012276803,
      "market_cap": 51574950.50236462,
      "volume_24h": 80303438.67776735,
      "pct_7d": -16.37544561,
      "pct_30d": -52.70198618,
      "float_ratio": 0.388480994201,
      "score": 0.513342144755787,
      "parts": {
        "float_quality": 0.388480994201,
        "momentum_24h": 0,
        "momentum_7d": 0,
        "momentum_30d": 0,
        "volume_surge": 1
      },
      "dd": {
        "tvl": 0,
        "category": "CDP",
        "fees24h": null,
        "liquidity_usd": 66889.29,
        "pair_age_days": null,
        "token_age_days": null,
        "flags": [
          {
            "k": "liquidité faible",
            "t": "bad"
          }
        ]
      }
    },
    {
      "id": 36828,
      "symbol": "USELESS",
      "name": "Useless Coin",
      "price": 0.0699603775399894,
      "market_cap": 69896344.59377708,
      "volume_24h": 12059949.96660029,
      "pct_7d": -14.96781312,
      "pct_30d": -13.52604265,
      "float_ratio": 1,
      "score": 0.5122644001147282,
      "parts": {
        "float_quality": 1,
        "momentum_24h": 0,
        "momentum_7d": 0,
        "momentum_30d": 0,
        "volume_surge": 0.3450809920515928
      },
      "dd": {
        "tvl": null,
        "category": null,
        "fees24h": null,
        "liquidity_usd": 2054480.83,
        "pair_age_days": 431,
        "token_age_days": null,
        "flags": []
      }
    },
    {
      "id": 23095,
      "symbol": "BONK",
      "name": "Bonk",
      "price": 0.000003555915157986009,
      "market_cap": 312901345.6296593,
      "volume_24h": 53405782.61737375,
      "pct_7d": -11.1073779,
      "pct_30d": -25.68768014,
      "float_ratio": 1,
      "score": 0.5109131717448843,
      "parts": {
        "float_quality": 1,
        "momentum_24h": 0,
        "momentum_7d": 0,
        "momentum_30d": 0,
        "volume_surge": 0.34135859984816586
      },
      "dd": {
        "tvl": 10550493.006783528,
        "category": "Liquid Staking",
        "fees24h": 0,
        "liquidity_usd": null,
        "pair_age_days": null,
        "token_age_days": null,
        "flags": [
          {
            "k": "TVL sans revenu",
            "t": "warn"
          }
        ]
      }
    },
    {
      "id": 33788,
      "symbol": "PNUT",
      "name": "Peanut the Squirrel",
      "price": 0.042602923233449254,
      "market_cap": 42596181.11026489,
      "volume_24h": 7140233.20042949,
      "pct_7d": -0.06331185,
      "pct_30d": -6.70419869,
      "float_ratio": 1,
      "score": 0.5086965739274362,
      "parts": {
        "float_quality": 1,
        "momentum_24h": 0,
        "momentum_7d": 0,
        "momentum_30d": 0,
        "volume_surge": 0.33525226977255135
      },
      "dd": {
        "tvl": null,
        "category": null,
        "fees24h": null,
        "liquidity_usd": 2600103.68,
        "pair_age_days": 622,
        "token_age_days": null,
        "flags": []
      }
    },
    {
      "id": 33824,
      "symbol": "SYRUP",
      "name": "Maple Finance",
      "price": 0.18717393792163137,
      "market_cap": 222925902.06462693,
      "volume_24h": 23132603.76476696,
      "pct_7d": 18.06747391,
      "pct_30d": 31.93354479,
      "float_ratio": 0.9568818541486134,
      "score": 0.507914171778147,
      "parts": {
        "float_quality": 0.9568818541486134,
        "momentum_24h": 0.029068348666666667,
        "momentum_7d": 0.3613494782,
        "momentum_30d": 0.3193354479,
        "volume_surge": 0.20753625801689699
      },
      "dd": {
        "tvl": 2355483868.440717,
        "category": "Lending",
        "fees24h": 587031,
        "liquidity_usd": 2005386.12,
        "pair_age_days": 459,
        "token_age_days": null,
        "flags": [
          {
            "k": "revenu réel",
            "t": "ok"
          }
        ]
      }
    },
    {
      "id": 29814,
      "symbol": "ETHFI",
      "name": "ether.fi",
      "price": 0.4306418051120888,
      "market_cap": 399362697.00147706,
      "volume_24h": 60736000.47091033,
      "pct_7d": 3.97370393,
      "pct_30d": 25.59673974,
      "float_ratio": 0.927366299,
      "score": 0.5071832273643733,
      "parts": {
        "float_quality": 0.927366299,
        "momentum_24h": 0.143143357,
        "momentum_7d": 0.0794740786,
        "momentum_30d": 0.2559673974,
        "volume_surge": 0.30416461490736424
      },
      "dd": {
        "tvl": 3120116315.5054417,
        "category": "Liquid Restaking",
        "fees24h": null,
        "liquidity_usd": 728983.67,
        "pair_age_days": 345,
        "token_age_days": null,
        "flags": [
          {
            "k": "TVL sans revenu",
            "t": "warn"
          }
        ]
      }
    },
    {
      "id": 38093,
      "symbol": "NVDAon",
      "name": "NVIDIA Tokenized Stock (Ondo)",
      "price": 209.31515521065734,
      "market_cap": 41040253.598573305,
      "volume_24h": 6491207.36980865,
      "pct_7d": 2.2367978,
      "pct_30d": -1.28596929,
      "float_ratio": 1,
      "score": 0.5063027240107685,
      "parts": {
        "float_quality": 1,
        "momentum_24h": 0,
        "momentum_7d": 0.044735956,
        "momentum_30d": 0,
        "volume_surge": 0.316333687082007
      },
      "dd": {
        "tvl": null,
        "category": null,
        "fees24h": null,
        "liquidity_usd": null,
        "pair_age_days": null,
        "token_age_days": null,
        "flags": []
      }
    },
    {
      "id": 40092,
      "symbol": "O",
      "name": "o1.exchange",
      "price": 0.5390661217552836,
      "market_cap": 86250579.48084538,
      "volume_24h": 286093820.07437485,
      "pct_7d": -3.72119809,
      "pct_30d": 722.01769831,
      "float_ratio": 0.16,
      "score": 0.49992,
      "parts": {
        "float_quality": 0.16,
        "momentum_24h": 0,
        "momentum_7d": 0,
        "momentum_30d": 1,
        "volume_surge": 1
      },
      "dd": {
        "tvl": 767730.0273101894,
        "category": "Staking Rental",
        "fees24h": null,
        "liquidity_usd": 2610431.05,
        "pair_age_days": 31,
        "token_age_days": null,
        "flags": [
          {
            "k": "TVL sans revenu",
            "t": "warn"
          }
        ]
      }
    },
    {
      "id": 38339,
      "symbol": "UB",
      "name": "Unibase",
      "price": 0.08099839506647526,
      "market_cap": 202495987.66618815,
      "volume_24h": 142259534.01310867,
      "pct_7d": 19.13441061,
      "pct_30d": -30.4374055,
      "float_ratio": 0.25,
      "score": 0.49801882121999996,
      "parts": {
        "float_quality": 0.25,
        "momentum_24h": 0,
        "momentum_7d": 0.3826882122,
        "momentum_30d": 0,
        "volume_surge": 1
      },
      "dd": {
        "tvl": null,
        "category": null,
        "fees24h": null,
        "liquidity_usd": null,
        "pair_age_days": null,
        "token_age_days": null,
        "flags": []
      }
    },
    {
      "id": 6758,
      "symbol": "SUSHI",
      "name": "SushiSwap",
      "price": 0.16821798164939353,
      "market_cap": 48250810.83185218,
      "volume_24h": 6682849.8126307,
      "pct_7d": 4.79206178,
      "pct_30d": -9.06417055,
      "float_ratio": 0.9839468919455162,
      "score": 0.4949848070724466,
      "parts": {
        "float_quality": 0.9839468919455162,
        "momentum_24h": 0.054140579,
        "momentum_7d": 0.0958412356,
        "momentum_30d": 0,
        "volume_surge": 0.2770046636488479
      },
      "dd": {
        "tvl": 39975578.93378838,
        "category": "Dexs",
        "fees24h": 7338,
        "liquidity_usd": 770818.67,
        "pair_age_days": 1197,
        "token_age_days": null,
        "flags": [
          {
            "k": "revenu réel",
            "t": "ok"
          }
        ]
      }
    }
  ]
}